Workbook

Sheet Guide
A1: HRSS Service Desk Tracker
A2: Portfolio project - synthetic data only. Built to mirror an HR Support Services (Ireland process) desk.
A4: Purpose | B4: Log, track and report HR support requests against SLA, with GDPR-aware data handling.
A6: SHEET | B6: WHAT IT DOES
A7: Dashboard | B7: KPIs, SLA compliance by request type, scheme volumes, chart. All formulas - updates automatically.
A8: Request_Tracker | B8: Master log for all 6 request types. SLA due date, status, SLA result, turnaround auto-calculate.
A9: Letter_Generator | B9: Pick an Employee ID -> reference letter and salary certificate text build themselves (replaces manual mail merge).
A10: Coach_Changes | B10: Validates coach changes: not self, coach active, capacity limit, not already assigned.
A11: Bike_to_Work | B11: Checks item cap and repeat-claim gap before approval.
A12: Eyecare_VDU | B12: Checks VDU-user flag and repeat-voucher gap; calculates voucher expiry.
A13: Milestones | B13: Perx vouchers, flowers and baby gifts: event -> gift/value lookup, delivery check, dispatch date.
A14: Quality_Log | B14: Four-eyes QC log: first-time-right %, errors caught, automatic escalation for wrong-recipient (possible data breach).
A15: Handover_Log | B15: Shift handover between agents/time zones: at-risk items, priority actions, acknowledgement.
A16: Worker_History | B16: Effective-dated job history + as-of lookup (title/department on a given date) - Workday-style concept.
... A19: Lists | B19: All configurable rules: SLA days, scheme limits, gift values, holidays, dropdown lists.
A21: COLOUR LEGEND
A22: Yellow cell, blue text | B22: Input - type or pick from dropdown here.
A23: Grey cell | B23: Formula - do not overwrite.
A25: HOW TO USE | B25: 1) Add employee to Employees 2) Log request in Request_Tracker (type, Emp ID, date received, purpose) 3) Do the work (use scheme sheet / Letter_Generator) 4) Enter Date Closed 5) Check Dashboard.
A27: ASSUMPTIONS | B27: SLA days, scheme caps/gaps, gift values and the 2026 Irish holiday list are illustrative and editable in Lists. Verify against actual policy and Revenue.ie before real use.
B28: Report date on Lists!E4 is =TODAY(). Overwrite it with a fixed date to freeze a report.
B29: SLA is measured in WORKING days (Mon-Fri excluding holidays in Lists). Compliance % = Met / (Met + Breached + Overdue); open items still inside SLA are excluded.
A30: GDPR | B30: No real personal data. Salary sits only on Employees (restricted) and Letter_Generator; the tracker shows name only (data minimisation). Every request records a purpose of data access.

Sheet Dashboard
A1: HRSS Dashboard
A2: Auto-calculated from Request_Tracker. Compliance % = Met / (Met + Breached + Overdue).
A3: Report date | B3: =Lists!E4 -> 46297
A5: Total requests | B5: Closed | C5: Open | D5: Open & overdue | E5: Closed late (breached) | F5: SLA compliance % | G5: Avg turnaround (working days, closed)
A6: =COUNTA(Request_Tracker!$B$6:$B$205) -> 12 | B6: =COUNTIF(Request_Tracker!$J$6:$J$205,"Closed") -> 8 | C6: =COUNTIF(Request_Tracker!$J$6:$J$205,"Open") -> 4 | D6: =COUNTIF(Request_Tracker!$K$6:$K$205,"Overdue") -> 0 | E6: =COUNTIF(Request_Tracker!$K$6:$K$205,"Breached") -> 2 | F6: =IFERROR(COUNTIF(Request_Tracker!$K$6:$K$205,"Met")/(COUNTIF(Request_Tracker!$K$6:$K$205,"Met")+COUNTIF(Request_Tracker!$K$6:$K$205,"Breached")+COUNTIF(Request_Tracker!$K$6:$K$205,"Overdue")),0) -> 0.75 | G6: =IFERROR(AVERAGEIF(Request_Tracker!$J$6:$J$205,"Closed",Request_Tracker!$L$6:$L$205),0) -> 2
A9: Request Type | B9: Total | C9: Met | D9: Breached | E9: Overdue | F9: Open - within SLA | G9: Compliance %
A10: =Lists!A4 -> Reference Letter | B10: =COUNTIF(Request_Tracker!$B$6:$B$205,A10) -> 3 | C10: =COUNTIFS(Request_Tracker!$B$6:$B$205,$A10,Request_Tracker!$K$6:$K$205,"Met") -> 2 | D10: =COUNTIFS(Request_Tracker!$B$6:$B$205,$A10,Request_Tracker!$K$6:$K$205,"Breached") -> 0 | E10: =COUNTIFS(Request_Tracker!$B$6:$B$205,$A10,Request_Tracker!$K$6:$K$205,"Overdue") -> 0 | F10: =COUNTIFS(Request_Tracker!$B$6:$B$205,$A10,Request_Tracker!$K$6:$K$205,"Open - within SLA") -> 1 | G10: =IFERROR(C10/(C10+D10+E10),"-") -> 1
A11: =Lists!A5 -> Salary Certificate | B11: =COUNTIF(Request_Tracker!$B$6:$B$205,A11) -> 3 | C11: =COUNTIFS(Request_Tracker!$B$6:$B$205,$A11,Request_Tracker!$K$6:$K$205,"Met") -> 1 | D11: =COUNTIFS(Request_Tracker!$B$6:$B$205,$A11,Request_Tracker!$K$6:$K$205,"Breached") -> 1 | E11: =COUNTIFS(Request_Tracker!$B$6:$B$205,$A11,Request_Tracker!$K$6:$K$205,"Overdue") -> 0 | F11: =COUNTIFS(Request_Tracker!$B$6:$B$205,$A11,Request_Tracker!$K$6:$K$205,"Open - within SLA") -> 1 | G11: =IFERROR(C11/(C11+D11+E11),"-") -> 0.5
A12: =Lists!A6 -> Coach Change | B12: =COUNTIF(Request_Tracker!$B$6:$B$205,A12) -> 2 | C12: =COUNTIFS(Request_Tracker!$B$6:$B$205,$A12,Request_Tracker!$K$6:$K$205,"Met") -> 0 | D12: =COUNTIFS(Request_Tracker!$B$6:$B$205,$A12,Request_Tracker!$K$6:$K$205,"Breached") -> 1 | E12: =COUNTIFS(Request_Tracker!$B$6:$B$205,$A12,Request_Tracker!$K$6:$K$205,"Overdue") -> 0 | F12: =COUNTIFS(Request_Tracker!$B$6:$B$205,$A12,Request_Tracker!$K$6:$K$205,"Open - within SLA") -> 1 | G12: =IFERROR(C12/(C12+D12+E12),"-") -> 0
A13: =Lists!A7 -> Bike to Work | B13: =COUNTIF(Request_Tracker!$B$6:$B$205,A13) -> 2 | C13: =COUNTIFS(Request_Tracker!$B$6:$B$205,$A13,Request_Tracker!$K$6:$K$205,"Met") -> 1 | D13: =COUNTIFS(Request_Tracker!$B$6:$B$205,$A13,Request_Tracker!$K$6:$K$205,"Breached") -> 0 | E13: =COUNTIFS(Request_Tracker!$B$6:$B$205,$A13,Request_Tracker!$K$6:$K$205,"Overdue") -> 0 | F13: =COUNTIFS(Request_Tracker!$B$6:$B$205,$A13,Request_Tracker!$K$6:$K$205,"Open - within SLA") -> 1 | G13: =IFERROR(C13/(C13+D13+E13),"-") -> 1
A14: =Lists!A8 -> Eyecare / VDU Voucher | B14: =COUNTIF(Request_Tracker!$B$6:$B$205,A14) -> 1 | C14: =COUNTIFS(Request_Tracker!$B$6:$B$205,$A14,Request_Tracker!$K$6:$K$205,"Met") -> 1 | D14: =COUNTIFS(Request_Tracker!$B$6:$B$205,$A14,Request_Tracker!$K$6:$K$205,"Breached") -> 0 | E14: =COUNTIFS(Request_Tracker!$B$6:$B$205,$A14,Request_Tracker!$K$6:$K$205,"Overdue") -> 0 | F14: =COUNTIFS(Request_Tracker!$B$6:$B$205,$A14,Request_Tracker!$K$6:$K$205,"Open - within SLA") -> 0 | G14: =IFERROR(C14/(C14+D14+E14),"-") -> 1
A15: =Lists!A9 -> Personal Milestone | B15: =COUNTIF(Request_Tracker!$B$6:$B$205,A15) -> 1 | C15: =COUNTIFS(Request_Tracker!$B$6:$B$205,$A15,Request_Tracker!$K$6:$K$205,"Met") -> 1 | D15: =COUNTIFS(Request_Tracker!$B$6:$B$205,$A15,Request_Tracker!$K$6:$K$205,"Breached") -> 0 | E15: =COUNTIFS(Request_Tracker!$B$6:$B$205,$A15,Request_Tracker!$K$6:$K$205,"Overdue") -> 0 | F15: =COUNTIFS(Request_Tracker!$B$6:$B$205,$A15,Request_Tracker!$K$6:$K$205,"Open - within SLA") -> 0 | G15: =IFERROR(C15/(C15+D15+E15),"-") -> 1
A16: =Lists!A10 -> Ad-hoc / Other | B16: =COUNTIF(Request_Tracker!$B$6:$B$205,A16) -> 0 | C16: =COUNTIFS(Request_Tracker!$B$6:$B$205,$A16,Request_Tracker!$K$6:$K$205,"Met") -> 0 | D16: =COUNTIFS(Request_Tracker!$B$6:$B$205,$A16,Request_Tracker!$K$6:$K$205,"Breached") -> 0 | E16: =COUNTIFS(Request_Tracker!$B$6:$B$205,$A16,Request_Tracker!$K$6:$K$205,"Overdue") -> 0 | F16: =COUNTIFS(Request_Tracker!$B$6:$B$205,$A16,Request_Tracker!$K$6:$K$205,"Open - within SLA") -> 0 | G16: =IFERROR(C16/(C16+D16+E16),"-") -> -
A17: TOTAL | B17: =SUM(B10:B16) -> 12 | C17: =SUM(C10:C16) -> 6 | D17: =SUM(D10:D16) -> 2 | E17: =SUM(E10:E16) -> 0 | F17: =SUM(F10:F16) -> 4 | G17: =IFERROR(C17/(C17+D17+E17),"-") -> 0.75
A20: Scheme activity
A21: Coach changes logged | B21: =COUNTA(Coach_Changes!B5:B104) -> 2
A22: of which valid | B22: =COUNTIF(Coach_Changes!J5:J104,"OK") -> 1
A23: Bike to Work applications | B23: =COUNTA(Bike_to_Work!B5:B104) -> 2
A24: of which eligible | B24: =COUNTIF(Bike_to_Work!J5:J104,"Eligible") -> 1
A25: Eyecare vouchers requested | B25: =COUNTA(Eyecare_VDU!B5:B104) -> 2
A26: of which eligible | B26: =COUNTIF(Eyecare_VDU!G5:G104,"Eligible") -> 1
A27: Milestone gifts logged | B27: =COUNTA(Milestones!B5:B104) -> 2
A28: Milestone value (EUR) | B28: =SUM(Milestones!F5:F104) -> 225
A31: Quality (accuracy) - from Quality_Log
A32: QC checks performed | B32: =COUNTA(Quality_Log!B5:B204) -> 12
A33: First-time-right % | B33: =IFERROR(COUNTIF(Quality_Log!E5:E204,"Pass")/COUNTA(Quality_Log!B5:B204),0) -> 0.83333333
A34: Errors caught before release | B34: =COUNTIFS(Quality_Log!E5:E204,"Fail",Quality_Log!G5:G204,"Yes") -> 1
A35: Items needing escalation | B35: =SUMPRODUCT(--(LEFT(Quality_Log!H5:H204,8)="ESCALATE")) -> 1

Sheet Request_Tracker
A1: Request Tracker
A2: Yellow = input, grey = formula. SAMPLE DATA in rows 6-17 - overwrite or clear. SLA in working days (see Lists).
A5: Req ID | B5: Request Type | C5: Emp ID | D5: Employee Name | E5: Date Received | F5: SLA (working days) | G5: Due Date | H5: Assigned To | I5: Date Closed | J5: Status | K5: SLA Result | L5: Turnaround (working days) | M5: Purpose of Data Access | N5: Notes / Case Ref
A6: REQ-0001 | B6: Salary Certificate | C6: E1001 | D6: =IF(C6="","",IFERROR(INDEX(Employees!$B$5:$B$200,MATCH(C6,Employees!$A$5:$A$200,0)),"ID not found")) -> Aoife Murphy | E6: 46286 | F6: =IF(B6="","",IFERROR(INDEX(Lists!$B$4:$B$10,MATCH(B6,Lists!$A$4:$A$10,0)),"")) -> 1 | G6: =IF(OR(E6="",F6=""),"",WORKDAY(E6,F6,Lists!$L$4:$L$13)) -> 46287 | H6: Agent 1 | I6: 46286 | J6: =IF(B6="","",IF(I6="","Open","Closed")) -> Closed | K6: =IF(G6="","",IF(I6="",IF(Lists!$E$4>G6,"Overdue","Open - within SLA"),IF(I6<=G6,"Met","Breached"))) -> Met | L6: =IF(E6="","",MAX(0,NETWORKDAYS(E6,IF(I6="",Lists!$E$4,I6),Lists!$L$4:$L$13)-1)) -> 0 | M6: Employee-requested document | N6: Mortgage application
A7: REQ-0002 | B7: Reference Letter | C7: E1004 | D7: =IF(C7="","",IFERROR(INDEX(Employees!$B$5:$B$200,MATCH(C7,Employees!$A$5:$A$200,0)),"ID not found")) -> Sean Doyle | E7: 46286 | F7: =IF(B7="","",IFERROR(INDEX(Lists!$B$4:$B$10,MATCH(B7,Lists!$A$4:$A$10,0)),"")) -> 2 | G7: =IF(OR(E7="",F7=""),"",WORKDAY(E7,F7,Lists!$L$4:$L$13)) -> 46288 | H7: Agent 2 | I7: 46287 | J7: =IF(B7="","",IF(I7="","Open","Closed")) -> Closed | K7: =IF(G7="","",IF(I7="",IF(Lists!$E$4>G7,"Overdue","Open - within SLA"),IF(I7<=G7,"Met","Breached"))) -> Met | L7: =IF(E7="","",MAX(0,NETWORKDAYS(E7,IF(I7="",Lists!$E$4,I7),Lists!$L$4:$L$13)-1)) -> 1 | M7: Employee-requested document | N7: Former employee - new employer
A8: REQ-0003 | B8: Coach Change | C8: E1002 | D8: =IF(C8="","",IFERROR(INDEX(Employees!$B$5:$B$200,MATCH(C8,Employees!$A$5:$A$200,0)),"ID not found")) -> Conor Walsh | E8: 46287 | F8: =IF(B8="","",IFERROR(INDEX(Lists!$B$4:$B$10,MATCH(B8,Lists!$A$4:$A$10,0)),"")) -> 3 | G8: =IF(OR(E8="",F8=""),"",WORKDAY(E8,F8,Lists!$L$4:$L$13)) -> 46290 | H8: Agent 1 | I8: 46293 | J8: =IF(B8="","",IF(I8="","Open","Closed")) -> Closed | K8: =IF(G8="","",IF(I8="",IF(Lists!$E$4>G8,"Overdue","Open - within SLA"),IF(I8<=G8,"Met","Breached"))) -> Breached | L8: =IF(E8="","",MAX(0,NETWORKDAYS(E8,IF(I8="",Lists!$E$4,I8),Lists!$L$4:$L$13)-1)) -> 4 | M8: Internal HR administration | N8: Awaiting new coach confirmation
A9: REQ-0004 | B9: Bike to Work | C9: E1003 | D9: =IF(C9="","",IFERROR(INDEX(Employees!$B$5:$B$200,MATCH(C9,Employees!$A$5:$A$200,0)),"ID not found")) -> Niamh Byrne | E9: 46288 | F9: =IF(B9="","",IFERROR(INDEX(Lists!$B$4:$B$10,MATCH(B9,Lists!$A$4:$A$10,0)),"")) -> 4 | G9: =IF(OR(E9="",F9=""),"",WORKDAY(E9,F9,Lists!$L$4:$L$13)) -> 46294 | H9: Agent 2 | I9: 46294 | J9: =IF(B9="","",IF(I9="","Open","Closed")) -> Closed | K9: =IF(G9="","",IF(I9="",IF(Lists!$E$4>G9,"Overdue","Open - within SLA"),IF(I9<=G9,"Met","Breached"))) -> Met | L9: =IF(E9="","",MAX(0,NETWORKDAYS(E9,IF(I9="",Lists!$E$4,I9),Lists!$L$4:$L$13)-1)) -> 4 | M9: Benefit administration | N9: E-bike EUR 1,400
A10: REQ-0005 | B10: Eyecare / VDU Voucher | C10: E1001 | D10: =IF(C10="","",IFERROR(INDEX(Employees!$B$5:$B$200,MATCH(C10,Employees!$A$5:$A$200,0)),"ID not found")) -> Aoife Murphy | E10: 46289 | F10: =IF(B10="","",IFERROR(INDEX(Lists!$B$4:$B$10,MATCH(B10,Lists!$A$4:$A$10,0)),"")) -> 2 | G10: =IF(OR(E10="",F10=""),"",WORKDAY(E10,F10,Lists!$L$4:$L$13)) -> 46293 | H10: Agent 1 | I10: 46290 | J10: =IF(B10="","",IF(I10="","Open","Closed")) -> Closed | K10: =IF(G10="","",IF(I10="",IF(Lists!$E$4>G10,"Overdue","Open - within SLA"),IF(I10<=G10,"Met","Breached"))) -> Met | L10: =IF(E10="","",MAX(0,NETWORKDAYS(E10,IF(I10="",Lists!$E$4,I10),Lists!$L$4:$L$13)-1)) -> 1 | M10: Health & safety (VDU)
A11: REQ-0006 | B11: Personal Milestone | C11: E1002 | D11: =IF(C11="","",IFERROR(INDEX(Employees!$B$5:$B$200,MATCH(C11,Employees!$A$5:$A$200,0)),"ID not found")) -> Conor Walsh | E11: 46290 | F11: =IF(B11="","",IFERROR(INDEX(Lists!$B$4:$B$10,MATCH(B11,Lists!$A$4:$A$10,0)),"")) -> 3 | G11: =IF(OR(E11="",F11=""),"",WORKDAY(E11,F11,Lists!$L$4:$L$13)) -> 46295 | H11: Agent 2 | I11: 46294 | J11: =IF(B11="","",IF(I11="","Open","Closed")) -> Closed | K11: =IF(G11="","",IF(I11="",IF(Lists!$E$4>G11,"Overdue","Open - within SLA"),IF(I11<=G11,"Met","Breached"))) -> Met | L11: =IF(E11="","",MAX(0,NETWORKDAYS(E11,IF(I11="",Lists!$E$4,I11),Lists!$L$4:$L$13)-1)) -> 2 | M11: Employee recognition | N11: Baby gift
A12: REQ-0007 | B12: Salary Certificate | C12: E1006 | D12: =IF(C12="","",IFERROR(INDEX(Employees!$B$5:$B$200,MATCH(C12,Employees!$A$5:$A$200,0)),"ID not found")) -> Liam O'Brien | E12: 46293 | F12: =IF(B12="","",IFERROR(INDEX(Lists!$B$4:$B$10,MATCH(B12,Lists!$A$4:$A$10,0)),"")) -> 1 | G12: =IF(OR(E12="",F12=""),"",WORKDAY(E12,F12,Lists!$L$4:$L$13)) -> 46294 | H12: Agent 1 | I12: 46295 | J12: =IF(B12="","",IF(I12="","Open","Closed")) -> Closed | K12: =IF(G12="","",IF(I12="",IF(Lists!$E$4>G12,"Overdue","Open - within SLA"),IF(I12<=G12,"Met","Breached"))) -> Breached | L12: =IF(E12="","",MAX(0,NETWORKDAYS(E12,IF(I12="",Lists!$E$4,I12),Lists!$L$4:$L$13)-1)) -> 2 | M12: Employee-requested document | N12: Rental application
A13: REQ-0008 | B13: Reference Letter | C13: E1008 | D13: =IF(C13="","",IFERROR(INDEX(Employees!$B$5:$B$200,MATCH(C13,Employees!$A$5:$A$200,0)),"ID not found")) -> Patrick Nolan | E13: 46294 | F13: =IF(B13="","",IFERROR(INDEX(Lists!$B$4:$B$10,MATCH(B13,Lists!$A$4:$A$10,0)),"")) -> 2 | G13: =IF(OR(E13="",F13=""),"",WORKDAY(E13,F13,Lists!$L$4:$L$13)) -> 46296 | H13: Agent 2 | I13: 46296 | J13: =IF(B13="","",IF(I13="","Open","Closed")) -> Closed | K13: =IF(G13="","",IF(I13="",IF(Lists!$E$4>G13,"Overdue","Open - within SLA"),IF(I13<=G13,"Met","Breached"))) -> Met | L13: =IF(E13="","",MAX(0,NETWORKDAYS(E13,IF(I13="",Lists!$E$4,I13),Lists!$L$4:$L$13)-1)) -> 2 | M13: Employee-requested document
A14: REQ-0009 | B14: Reference Letter | C14: E1004 | D14: =IF(C14="","",IFERROR(INDEX(Employees!$B$5:$B$200,MATCH(C14,Employees!$A$5:$A$200,0)),"ID not found")) -> Sean Doyle | E14: 46295 | F14: =IF(B14="","",IFERROR(INDEX(Lists!$B$4:$B$10,MATCH(B14,Lists!$A$4:$A$10,0)),"")) -> 2 | G14: =IF(OR(E14="",F14=""),"",WORKDAY(E14,F14,Lists!$L$4:$L$13)) -> 46297 | H14: Agent 1 | J14: =IF(B14="","",IF(I14="","Open","Closed")) -> Open | K14: =IF(G14="","",IF(I14="",IF(Lists!$E$4>G14,"Overdue","Open - within SLA"),IF(I14<=G14,"Met","Breached"))) -> Open - within SLA | L14: =IF(E14="","",MAX(0,NETWORKDAYS(E14,IF(I14="",Lists!$E$4,I14),Lists!$L$4:$L$13)-1)) -> 2 | M14: Employee-requested document | N14: Second copy requested
A15: REQ-0010 | B15: Coach Change | C15: E1007 | D15: =IF(C15="","",IFERROR(INDEX(Employees!$B$5:$B$200,MATCH(C15,Employees!$A$5:$A$200,0)),"ID not found")) -> Emma Ryan | E15: 46295 | F15: =IF(B15="","",IFERROR(INDEX(Lists!$B$4:$B$10,MATCH(B15,Lists!$A$4:$A$10,0)),"")) -> 3 | G15: =IF(OR(E15="",F15=""),"",WORKDAY(E15,F15,Lists!$L$4:$L$13)) -> 46300 | H15: Agent 2 | J15: =IF(B15="","",IF(I15="","Open","Closed")) -> Open | K15: =IF(G15="","",IF(I15="",IF(Lists!$E$4>G15,"Overdue","Open - within SLA"),IF(I15<=G15,"Met","Breached"))) -> Open - within SLA | L15: =IF(E15="","",MAX(0,NETWORKDAYS(E15,IF(I15="",Lists!$E$4,I15),Lists!$L$4:$L$13)-1)) -> 2 | M15: Internal HR administration
A16: REQ-0011 | B16: Bike to Work | C16: E1005 | D16: =IF(C16="","",IFERROR(INDEX(Employees!$B$5:$B$200,MATCH(C16,Employees!$A$5:$A$200,0)),"ID not found")) -> Ciara Kelly | E16: 46296 | F16: =IF(B16="","",IFERROR(INDEX(Lists!$B$4:$B$10,MATCH(B16,Lists!$A$4:$A$10,0)),"")) -> 4 | G16: =IF(OR(E16="",F16=""),"",WORKDAY(E16,F16,Lists!$L$4:$L$13)) -> 46302 | H16: Agent 1 | J16: =IF(B16="","",IF(I16="","Open","Closed")) -> Open | K16: =IF(G16="","",IF(I16="",IF(Lists!$E$4>G16,"Overdue","Open - within SLA"),IF(I16<=G16,"Met","Breached"))) -> Open - within SLA | L16: =IF(E16="","",MAX(0,NETWORKDAYS(E16,IF(I16="",Lists!$E$4,I16),Lists!$L$4:$L$13)-1)) -> 1 | M16: Benefit administration | N16: Bike EUR 950
A17: REQ-0012 | B17: Salary Certificate | C17: E1003 | D17: =IF(C17="","",IFERROR(INDEX(Employees!$B$5:$B$200,MATCH(C17,Employees!$A$5:$A$200,0)),"ID not found")) -> Niamh Byrne | E17: 46297 | F17: =IF(B17="","",IFERROR(INDEX(Lists!$B$4:$B$10,MATCH(B17,Lists!$A$4:$A$10,0)),"")) -> 1 | G17: =IF(OR(E17="",F17=""),"",WORKDAY(E17,F17,Lists!$L$4:$L$13)) -> 46300 | H17: Agent 2 | J17: =IF(B17="","",IF(I17="","Open","Closed")) -> Open | K17: =IF(G17="","",IF(I17="",IF(Lists!$E$4>G17,"Overdue","Open - within SLA"),IF(I17<=G17,"Met","Breached"))) -> Open - within SLA | L17: =IF(E17="","",MAX(0,NETWORKDAYS(E17,IF(I17="",Lists!$E$4,I17),Lists!$L$4:$L$13)-1)) -> 0 | M17: Employee-requested document | N17: Visa application
D18: =IF(C18="","",IFERROR(INDEX(Employees!$B$5:$B$200,MATCH(C18,Employees!$A$5:$A$200,0)),"ID not found")) | F18: =IF(B18="","",IFERROR(INDEX(Lists!$B$4:$B$10,MATCH(B18,Lists!$A$4:$A$10,0)),"")) | G18: =IF(OR(E18="",F18=""),"",WORKDAY(E18,F18,Lists!$L$4:$L$13)) | J18: =IF(B18="","",IF(I18="","Open","Closed")) | K18: =IF(G18="","",IF(I18="",IF(Lists!$E$4>G18,"Overdue","Open - within SLA"),IF(I18<=G18,"Met","Breached"))) | L18: =IF(E18="","",MAX(0,NETWORKDAYS(E18,IF(I18="",Lists!$E$4,I18),Lists!$L$4:$L$13)-1))
D19: =IF(C19="","",IFERROR(INDEX(Employees!$B$5:$B$200,MATCH(C19,Employees!$A$5:$A$200,0)),"ID not found")) | F19: =IF(B19="","",IFERROR(INDEX(Lists!$B$4:$B$10,MATCH(B19,Lists!$A$4:$A$10,0)),"")) | G19: =IF(OR(E19="",F19=""),"",WORKDAY(E19,F19,Lists!$L$4:$L$13)) | J19: =IF(B19="","",IF(I19="","Open","Closed")) | K19: =IF(G19="","",IF(I19="",IF(Lists!$E$4>G19,"Overdue","Open - within SLA"),IF(I19<=G19,"Met","Breached"))) | L19: =IF(E19="","",MAX(0,NETWORKDAYS(E19,IF(I19="",Lists!$E$4,I19),Lists!$L$4:$L$13)-1))
D20: =IF(C20="","",IFERROR(INDEX(Employees!$B$5:$B$200,MATCH(C20,Employees!$A$5:$A$200,0)),"ID not found")) | F20: =IF(B20="","",IFERROR(INDEX(Lists!$B$4:$B$10,MATCH(B20,Lists!$A$4:$A$10,0)),"")) | G20: =IF(OR(E20="",F20=""),"",WORKDAY(E20,F20,Lists!$L$4:$L$13)) | J20: =IF(B20="","",IF(I20="","Open","Closed")) | K20: =IF(G20="","",IF(I20="",IF(Lists!$E$4>G20,"Overdue","Open - within SLA"),IF(I20<=G20,"Met","Breached"))) | L20: =IF(E20="","",MAX(0,NETWORKDAYS(E20,IF(I20="",Lists!$E$4,I20),Lists!$L$4:$L$13)-1))
D21: =IF(C21="","",IFERROR(INDEX(Employees!$B$5:$B$200,MATCH(C21,Employees!$A$5:$A$200,0)),"ID not found")) | F21: =IF(B21="","",IFERROR(INDEX(Lists!$B$4:$B$10,MATCH(B21,Lists!$A$4:$A$10,0)),"")) | G21: =IF(OR(E21="",F21=""),"",WORKDAY(E21,F21,Lists!$L$4:$L$13)) | J21: =IF(B21="","",IF(I21="","Open","Closed")) | K21: =IF(G21="","",IF(I21="",IF(Lists!$E$4>G21,"Overdue","Open - within SLA"),IF(I21<=G21,"Met","Breached"))) | L21: =IF(E21="","",MAX(0,NETWORKDAYS(E21,IF(I21="",Lists!$E$4,I21),Lists!$L$4:$L$13)-1))
D22: =IF(C22="","",IFERROR(INDEX(Employees!$B$5:$B$200,MATCH(C22,Employees!$A$5:$A$200,0)),"ID not found")) | F22: =IF(B22="","",IFERROR(INDEX(Lists!$B$4:$B$10,MATCH(B22,Lists!$A$4:$A$10,0)),"")) | G22: =IF(OR(E22="",F22=""),"",WORKDAY(E22,F22,Lists!$L$4:$L$13)) | J22: =IF(B22="","",IF(I22="","Open","Closed")) | K22: =IF(G22="","",IF(I22="",IF(Lists!$E$4>G22,"Overdue","Open - within SLA"),IF(I22<=G22,"Met","Breached"))) | L22: =IF(E22="","",MAX(0,NETWORKDAYS(E22,IF(I22="",Lists!$E$4,I22),Lists!$L$4:$L$13)-1))
D23: =IF(C23="","",IFERROR(INDEX(Employees!$B$5:$B$200,MATCH(C23,Employees!$A$5:$A$200,0)),"ID not found")) | F23: =IF(B23="","",IFERROR(INDEX(Lists!$B$4:$B$10,MATCH(B23,Lists!$A$4:$A$10,0)),"")) | G23: =IF(OR(E23="",F23=""),"",WORKDAY(E23,F23,Lists!$L$4:$L$13)) | J23: =IF(B23="","",IF(I23="","Open","Closed")) | K23: =IF(G23="","",IF(I23="",IF(Lists!$E$4>G23,"Overdue","Open - within SLA"),IF(I23<=G23,"Met","Breached"))) | L23: =IF(E23="","",MAX(0,NETWORKDAYS(E23,IF(I23="",Lists!$E$4,I23),Lists!$L$4:$L$13)-1))
D24: =IF(C24="","",IFERROR(INDEX(Employees!$B$5:$B$200,MATCH(C24,Employees!$A$5:$A$200,0)),"ID not found")) | F24: =IF(B24="","",IFERROR(INDEX(Lists!$B$4:$B$10,MATCH(B24,Lists!$A$4:$A$10,0)),"")) | G24: =IF(OR(E24="",F24=""),"",WORKDAY(E24,F24,Lists!$L$4:$L$13)) | J24: =IF(B24="","",IF(I24="","Open","Closed")) | K24: =IF(G24="","",IF(I24="",IF(Lists!$E$4>G24,"Overdue","Open - within SLA"),IF(I24<=G24,"Met","Breached"))) | L24: =IF(E24="","",MAX(0,NETWORKDAYS(E24,IF(I24="",Lists!$E$4,I24),Lists!$L$4:$L$13)-1))
D25: =IF(C25="","",IFERROR(INDEX(Employees!$B$5:$B$200,MATCH(C25,Employees!$A$5:$A$200,0)),"ID not found")) | F25: =IF(B25="","",IFERROR(INDEX(Lists!$B$4:$B$10,MATCH(B25,Lists!$A$4:$A$10,0)),"")) | G25: =IF(OR(E25="",F25=""),"",WORKDAY(E25,F25,Lists!$L$4:$L$13)) | J25: =IF(B25="","",IF(I25="","Open","Closed")) | K25: =IF(G25="","",IF(I25="",IF(Lists!$E$4>G25,"Overdue","Open - within SLA"),IF(I25<=G25,"Met","Breached"))) | L25: =IF(E25="","",MAX(0,NETWORKDAYS(E25,IF(I25="",Lists!$E$4,I25),Lists!$L$4:$L$13)-1))
D26: =IF(C26="","",IFERROR(INDEX(Employees!$B$5:$B$200,MATCH(C26,Employees!$A$5:$A$200,0)),"ID not found")) | F26: =IF(B26="","",IFERROR(INDEX(Lists!$B$4:$B$10,MATCH(B26,Lists!$A$4:$A$10,0)),"")) | G26: =IF(OR(E26="",F26=""),"",WORKDAY(E26,F26,Lists!$L$4:$L$13)) | J26: =IF(B26="","",IF(I26="","Open","Closed")) | K26: =IF(G26="","",IF(I26="",IF(Lists!$E$4>G26,"Overdue","Open - within SLA"),IF(I26<=G26,"Met","Breached"))) | L26: =IF(E26="","",MAX(0,NETWORKDAYS(E26,IF(I26="",Lists!$E$4,I26),Lists!$L$4:$L$13)-1))
D27: =IF(C27="","",IFERROR(INDEX(Employees!$B$5:$B$200,MATCH(C27,Employees!$A$5:$A$200,0)),"ID not found")) | F27: =IF(B27="","",IFERROR(INDEX(Lists!$B$4:$B$10,MATCH(B27,Lists!$A$4:$A$10,0)),"")) | G27: =IF(OR(E27="",F27=""),"",WORKDAY(E27,F27,Lists!$L$4:$L$13)) | J27: =IF(B27="","",IF(I27="","Open","Closed")) | K27: =IF(G27="","",IF(I27="",IF(Lists!$E$4>G27,"Overdue","Open - within SLA"),IF(I27<=G27,"Met","Breached"))) | L27: =IF(E27="","",MAX(0,NETWORKDAYS(E27,IF(I27="",Lists!$E$4,I27),Lists!$L$4:$L$13)-1))
D28: =IF(C28="","",IFERROR(INDEX(Employees!$B$5:$B$200,MATCH(C28,Employees!$A$5:$A$200,0)),"ID not found")) | F28: =IF(B28="","",IFERROR(INDEX(Lists!$B$4:$B$10,MATCH(B28,Lists!$A$4:$A$10,0)),"")) | G28: =IF(OR(E28="",F28=""),"",WORKDAY(E28,F28,Lists!$L$4:$L$13)) | J28: =IF(B28="","",IF(I28="","Open","Closed")) | K28: =IF(G28="","",IF(I28="",IF(Lists!$E$4>G28,"Overdue","Open - within SLA"),IF(I28<=G28,"Met","Breached"))) | L28: =IF(E28="","",MAX(0,NETWORKDAYS(E28,IF(I28="",Lists!$E$4,I28),Lists!$L$4:$L$13)-1))
D29: =IF(C29="","",IFERROR(INDEX(Employees!$B$5:$B$200,MATCH(C29,Employees!$A$5:$A$200,0)),"ID not found")) | F29: =IF(B29="","",IFERROR(INDEX(Lists!$B$4:$B$10,MATCH(B29,Lists!$A$4:$A$10,0)),"")) | G29: =IF(OR(E29="",F29=""),"",WORKDAY(E29,F29,Lists!$L$4:$L$13)) | J29: =IF(B29="","",IF(I29="","Open","Closed")) | K29: =IF(G29="","",IF(I29="",IF(Lists!$E$4>G29,"Overdue","Open - within SLA"),IF(I29<=G29,"Met","Breached"))) | L29: =IF(E29="","",MAX(0,NETWORKDAYS(E29,IF(I29="",Lists!$E$4,I29),Lists!$L$4:$L$13)-1))
... D205: =IF(C205="","",IFERROR(INDEX(Employees!$B$5:$B$200,MATCH(C205,Employees!$A$5:$A$200,0)),"ID not found")) | F205: =IF(B205="","",IFERROR(INDEX(Lists!$B$4:$B$10,MATCH(B205,Lists!$A$4:$A$10,0)),"")) | G205: =IF(OR(E205="",F205=""),"",WORKDAY(E205,F205,Lists!$L$4:$L$13)) | J205: =IF(B205="","",IF(I205="","Open","Closed")) | K205: =IF(G205="","",IF(I205="",IF(Lists!$E$4>G205,"Overdue","Open - within SLA"),IF(I205<=G205,"Met","Breached"))) | L205: =IF(E205="","",MAX(0,NETWORKDAYS(E205,IF(I205="",Lists!$E$4,I205),Lists!$L$4:$L$13)-1))

Sheet Letter_Generator
A1: Letter Generator
A2: Enter Employee ID, purpose and issuer (yellow). Letters below build automatically - copy into Word / PDF.
A3: Employee ID | B3: E1001
A4: Purpose (salary cert) | B4: Mortgage application
A5: Issuer | B5: HRSS Agent 1
A6: Letter date | B6: =Lists!E4 -> 46297
A7: Row of employee | B7: =IFERROR(MATCH(B3,Employees!$A$5:$A$200,0),0) -> 1
A8: Name | B8: =IF($B$7=0,"ID not found",INDEX(Employees!$B$5:$B$200,$B$7)) -> Aoife Murphy
A9: Job title | B9: =IF($B$7=0,"",IF(INDEX(Employees!$D$5:$D$200,$B$7)="","",INDEX(Employees!$D$5:$D$200,$B$7))) -> Senior Consultant
A10: Department | B10: =IF($B$7=0,"",IF(INDEX(Employees!$F$5:$F$200,$B$7)="","",INDEX(Employees!$F$5:$F$200,$B$7))) -> Audit
A11: Grade | B11: =IF($B$7=0,"",IF(INDEX(Employees!$E$5:$E$200,$B$7)="","",INDEX(Employees!$E$5:$E$200,$B$7))) -> Senior
A12: Hire date | B12: =IF($B$7=0,"",IF(INDEX(Employees!$G$5:$G$200,$B$7)="","",INDEX(Employees!$G$5:$G$200,$B$7))) -> 43528
A13: End date | B13: =IF($B$7=0,"",IF(INDEX(Employees!$H$5:$H$200,$B$7)="","",INDEX(Employees!$H$5:$H$200,$B$7)))
A14: Status | B14: =IF($B$7=0,"",IF(INDEX(Employees!$I$5:$I$200,$B$7)="","",INDEX(Employees!$I$5:$I$200,$B$7))) -> active
A15: Annual salary (EUR) | B15: =IF($B$7=0,"",IF(INDEX(Employees!$L$5:$L$200,$B$7)="","",INDEX(Employees!$L$5:$L$200,$B$7))) -> 68000
A17: Reference letter status | B17: =IF($B$7=0,"Employee not found",IF(AND($B$14<>"active",$B$13=""),"Missing end date","Ready")) -> Ready
A18: Salary certificate status | B18: =IF($B$7=0,"Employee not found",IF($B$14<>"active","NOT ELIGIBLE - salary certificates are for current employees only",IF(TRIM($B$4)="","Purpose required","Ready"))) -> Ready
A20: ="REFERENCE LETTER | "&B17 -> REFERENCE LETTER | Ready
A21: =Lists!$E$11&CHAR(10)&"Ref: REF-"&TEXT($B$6,"yyyymmdd")&"-"&$B$3&CHAR(10)&"Date: "&TEXT($B$6,"dd mmmm yyyy") -> Example Company Ltd (Demo) Ref: REF-20261002-E1001 Date: 02 October 2026
A22: ="TO WHOM IT MAY CONCERN"&CHAR(10)&"Re: Employment Reference - "&$B$8 -> TO WHOM IT MAY CONCERN Re: Employment Reference - Aoife Murphy
A23: =IF($B$14="active",$B$8&" has been employed by "&Lists!$E$11&" since "&TEXT($B$12,"dd mmmm yyyy")&" and remains employed.",$B$8&" was employed by "&Lists!$E$11&" from "&TEXT($B$12,"dd mmmm yyyy")&" to "&IF($B$13="","[END DATE MISSING]",TEXT($B$13,"dd mmmm yyyy"))&".") -> Aoife Murphy has been employed by Example Company Ltd (Demo) since 04 March 2019 and remains employed.
A24: ="During this period, "&$B$8&" held the position of "&$B$9&" (Grade "&$B$11&") in the "&$B$10&" department." -> During this period, Aoife Murphy held the position of Senior Consultant (Grade Senior) in the Audit department.
A25: ="This reference is provided in confidence, at the employee's request, and relates only to employment dates and role held. It is issued without liability on the part of "&Lists!$E$11&"." -> This reference is provided in confidence, at the employee's request, and relates only to employment dates and role held. It is issued without liability on the part of Example Company Ltd (Demo).
A26: ="Yours faithfully,"&CHAR(10)&$B$5&CHAR(10)&"Human Resources Support Services" -> Yours faithfully, HRSS Agent 1 Human Resources Support Services
A28: ="SALARY CERTIFICATE | "&B18 -> SALARY CERTIFICATE | Ready
A29: =Lists!$E$11&CHAR(10)&"Ref: SAL-"&TEXT($B$6,"yyyymmdd")&"-"&$B$3&CHAR(10)&"Date: "&TEXT($B$6,"dd mmmm yyyy") -> Example Company Ltd (Demo) Ref: SAL-20261002-E1001 Date: 02 October 2026
A30: ="SALARY CERTIFICATE" -> SALARY CERTIFICATE
A31: ="This is to certify that "&$B$8&" (Employee ID: "&$B$3&") is employed by "&Lists!$E$11&" as "&$B$9&" in the "&$B$10&" department, with effect from "&TEXT($B$12,"dd mmmm yyyy")&"." -> This is to certify that Aoife Murphy (Employee ID: E1001) is employed by Example Company Ltd (Demo) as Senior Consultant in the Audit department, with effect from 04 March 2019.
A32: ="Gross annual salary: EUR "&TEXT($B$15,"#,##0.00") -> Gross annual salary: EUR 68,000.00
A33: ="Issued at the employee's request for the following purpose: "&$B$4&". It contains confidential personal data and must be used only for the stated purpose." -> Issued at the employee's request for the following purpose: Mortgage application. It contains confidential personal data and must be used only for the stated purpose.
A34: ="Yours faithfully,"&CHAR(10)&$B$5&CHAR(10)&"Human Resources Support Services" -> Yours faithfully, HRSS Agent 1 Human Resources Support Services

Sheet Coach_Changes
A1: Coach Changes
A2: Validation column checks rules before the change is actioned. SAMPLE rows 5-6.
A4: Date Requested | B4: Emp ID | C4: Employee Name | D4: Current Coach ID | E4: New Coach ID | F4: New Coach Name | G4: New Coach Status | H4: New Coach Current Load | I4: Capacity Check | J4: Validation | K4: Approved By | L4: Status
A5: 46287 | B5: E1002 | C5: =IF(B5="","",IFERROR(INDEX(Employees!$B$5:$B$200,MATCH(B5,Employees!$A$5:$A$200,0)),"ID not found")) -> Conor Walsh | D5: =IF(B5="","",IFERROR(INDEX(Employees!$J$5:$J$200,MATCH(B5,Employees!$A$5:$A$200,0))&"","ID not found")) -> E1005 | E5: E1006 | F5: =IF(E5="","",IFERROR(INDEX(Employees!$B$5:$B$200,MATCH(E5,Employees!$A$5:$A$200,0)),"ID not found")) -> Liam O'Brien | G5: =IF(E5="","",IFERROR(INDEX(Employees!$I$5:$I$200,MATCH(E5,Employees!$A$5:$A$200,0)),"not found")) -> active | H5: =IF(E5="","",COUNTIF(Employees!$J$5:$J$200,E5)) -> 2 | I5: =IF(E5="","",IF(H5>=Lists!$E$10,"At capacity","OK")) -> OK | J5: =IF(B5="","",IF(G5="not found","Invalid: coach ID not found",IF(B5=E5,"Invalid: self-coach",IF(G5<>"active","Invalid: coach inactive",IF(D5=E5,"Invalid: already assigned",IF(I5="At capacity","Invalid: at capacity","OK")))))) -> OK | K5: Agent 1 | L5: Completed
A6: 46295 | B6: E1007 | C6: =IF(B6="","",IFERROR(INDEX(Employees!$B$5:$B$200,MATCH(B6,Employees!$A$5:$A$200,0)),"ID not found")) -> Emma Ryan | D6: =IF(B6="","",IFERROR(INDEX(Employees!$J$5:$J$200,MATCH(B6,Employees!$A$5:$A$200,0))&"","ID not found")) -> E1006 | E6: E1007 | F6: =IF(E6="","",IFERROR(INDEX(Employees!$B$5:$B$200,MATCH(E6,Employees!$A$5:$A$200,0)),"ID not found")) -> Emma Ryan | G6: =IF(E6="","",IFERROR(INDEX(Employees!$I$5:$I$200,MATCH(E6,Employees!$A$5:$A$200,0)),"not found")) -> active | H6: =IF(E6="","",COUNTIF(Employees!$J$5:$J$200,E6)) -> 0 | I6: =IF(E6="","",IF(H6>=Lists!$E$10,"At capacity","OK")) -> OK | J6: =IF(B6="","",IF(G6="not found","Invalid: coach ID not found",IF(B6=E6,"Invalid: self-coach",IF(G6<>"active","Invalid: coach inactive",IF(D6=E6,"Invalid: already assigned",IF(I6="At capacity","Invalid: at capacity","OK")))))) -> Invalid: self-coach | K6: Agent 2 | L6: Pending
C7: =IF(B7="","",IFERROR(INDEX(Employees!$B$5:$B$200,MATCH(B7,Employees!$A$5:$A$200,0)),"ID not found")) | D7: =IF(B7="","",IFERROR(INDEX(Employees!$J$5:$J$200,MATCH(B7,Employees!$A$5:$A$200,0))&"","ID not found")) | F7: =IF(E7="","",IFERROR(INDEX(Employees!$B$5:$B$200,MATCH(E7,Employees!$A$5:$A$200,0)),"ID not found")) | G7: =IF(E7="","",IFERROR(INDEX(Employees!$I$5:$I$200,MATCH(E7,Employees!$A$5:$A$200,0)),"not found")) | H7: =IF(E7="","",COUNTIF(Employees!$J$5:$J$200,E7)) | I7: =IF(E7="","",IF(H7>=Lists!$E$10,"At capacity","OK")) | J7: =IF(B7="","",IF(G7="not found","Invalid: coach ID not found",IF(B7=E7,"Invalid: self-coach",IF(G7<>"active","Invalid: coach inactive",IF(D7=E7,"Invalid: already assigned",IF(I7="At capacity","Invalid: at capacity","OK"))))))
C8: =IF(B8="","",IFERROR(INDEX(Employees!$B$5:$B$200,MATCH(B8,Employees!$A$5:$A$200,0)),"ID not found")) | D8: =IF(B8="","",IFERROR(INDEX(Employees!$J$5:$J$200,MATCH(B8,Employees!$A$5:$A$200,0))&"","ID not found")) | F8: =IF(E8="","",IFERROR(INDEX(Employees!$B$5:$B$200,MATCH(E8,Employees!$A$5:$A$200,0)),"ID not found")) | G8: =IF(E8="","",IFERROR(INDEX(Employees!$I$5:$I$200,MATCH(E8,Employees!$A$5:$A$200,0)),"not found")) | H8: =IF(E8="","",COUNTIF(Employees!$J$5:$J$200,E8)) | I8: =IF(E8="","",IF(H8>=Lists!$E$10,"At capacity","OK")) | J8: =IF(B8="","",IF(G8="not found","Invalid: coach ID not found",IF(B8=E8,"Invalid: self-coach",IF(G8<>"active","Invalid: coach inactive",IF(D8=E8,"Invalid: already assigned",IF(I8="At capacity","Invalid: at capacity","OK"))))))
C9: =IF(B9="","",IFERROR(INDEX(Employees!$B$5:$B$200,MATCH(B9,Employees!$A$5:$A$200,0)),"ID not found")) | D9: =IF(B9="","",IFERROR(INDEX(Employees!$J$5:$J$200,MATCH(B9,Employees!$A$5:$A$200,0))&"","ID not found")) | F9: =IF(E9="","",IFERROR(INDEX(Employees!$B$5:$B$200,MATCH(E9,Employees!$A$5:$A$200,0)),"ID not found")) | G9: =IF(E9="","",IFERROR(INDEX(Employees!$I$5:$I$200,MATCH(E9,Employees!$A$5:$A$200,0)),"not found")) | H9: =IF(E9="","",COUNTIF(Employees!$J$5:$J$200,E9)) | I9: =IF(E9="","",IF(H9>=Lists!$E$10,"At capacity","OK")) | J9: =IF(B9="","",IF(G9="not found","Invalid: coach ID not found",IF(B9=E9,"Invalid: self-coach",IF(G9<>"active","Invalid: coach inactive",IF(D9=E9,"Invalid: already assigned",IF(I9="At capacity","Invalid: at capacity","OK"))))))
C10: =IF(B10="","",IFERROR(INDEX(Employees!$B$5:$B$200,MATCH(B10,Employees!$A$5:$A$200,0)),"ID not found")) | D10: =IF(B10="","",IFERROR(INDEX(Employees!$J$5:$J$200,MATCH(B10,Employees!$A$5:$A$200,0))&"","ID not found")) | F10: =IF(E10="","",IFERROR(INDEX(Employees!$B$5:$B$200,MATCH(E10,Employees!$A$5:$A$200,0)),"ID not found")) | G10: =IF(E10="","",IFERROR(INDEX(Employees!$I$5:$I$200,MATCH(E10,Employees!$A$5:$A$200,0)),"not found")) | H10: =IF(E10="","",COUNTIF(Employees!$J$5:$J$200,E10)) | I10: =IF(E10="","",IF(H10>=Lists!$E$10,"At capacity","OK")) | J10: =IF(B10="","",IF(G10="not found","Invalid: coach ID not found",IF(B10=E10,"Invalid: self-coach",IF(G10<>"active","Invalid: coach inactive",IF(D10=E10,"Invalid: already assigned",IF(I10="At capacity","Invalid: at capacity","OK"))))))
C11: =IF(B11="","",IFERROR(INDEX(Employees!$B$5:$B$200,MATCH(B11,Employees!$A$5:$A$200,0)),"ID not found")) | D11: =IF(B11="","",IFERROR(INDEX(Employees!$J$5:$J$200,MATCH(B11,Employees!$A$5:$A$200,0))&"","ID not found")) | F11: =IF(E11="","",IFERROR(INDEX(Employees!$B$5:$B$200,MATCH(E11,Employees!$A$5:$A$200,0)),"ID not found")) | G11: =IF(E11="","",IFERROR(INDEX(Employees!$I$5:$I$200,MATCH(E11,Employees!$A$5:$A$200,0)),"not found")) | H11: =IF(E11="","",COUNTIF(Employees!$J$5:$J$200,E11)) | I11: =IF(E11="","",IF(H11>=Lists!$E$10,"At capacity","OK")) | J11: =IF(B11="","",IF(G11="not found","Invalid: coach ID not found",IF(B11=E11,"Invalid: self-coach",IF(G11<>"active","Invalid: coach inactive",IF(D11=E11,"Invalid: already assigned",IF(I11="At capacity","Invalid: at capacity","OK"))))))
C12: =IF(B12="","",IFERROR(INDEX(Employees!$B$5:$B$200,MATCH(B12,Employees!$A$5:$A$200,0)),"ID not found")) | D12: =IF(B12="","",IFERROR(INDEX(Employees!$J$5:$J$200,MATCH(B12,Employees!$A$5:$A$200,0))&"","ID not found")) | F12: =IF(E12="","",IFERROR(INDEX(Employees!$B$5:$B$200,MATCH(E12,Employees!$A$5:$A$200,0)),"ID not found")) | G12: =IF(E12="","",IFERROR(INDEX(Employees!$I$5:$I$200,MATCH(E12,Employees!$A$5:$A$200,0)),"not found")) | H12: =IF(E12="","",COUNTIF(Employees!$J$5:$J$200,E12)) | I12: =IF(E12="","",IF(H12>=Lists!$E$10,"At capacity","OK")) | J12: =IF(B12="","",IF(G12="not found","Invalid: coach ID not found",IF(B12=E12,"Invalid: self-coach",IF(G12<>"active","Invalid: coach inactive",IF(D12=E12,"Invalid: already assigned",IF(I12="At capacity","Invalid: at capacity","OK"))))))
C13: =IF(B13="","",IFERROR(INDEX(Employees!$B$5:$B$200,MATCH(B13,Employees!$A$5:$A$200,0)),"ID not found")) | D13: =IF(B13="","",IFERROR(INDEX(Employees!$J$5:$J$200,MATCH(B13,Employees!$A$5:$A$200,0))&"","ID not found")) | F13: =IF(E13="","",IFERROR(INDEX(Employees!$B$5:$B$200,MATCH(E13,Employees!$A$5:$A$200,0)),"ID not found")) | G13: =IF(E13="","",IFERROR(INDEX(Employees!$I$5:$I$200,MATCH(E13,Employees!$A$5:$A$200,0)),"not found")) | H13: =IF(E13="","",COUNTIF(Employees!$J$5:$J$200,E13)) | I13: =IF(E13="","",IF(H13>=Lists!$E$10,"At capacity","OK")) | J13: =IF(B13="","",IF(G13="not found","Invalid: coach ID not found",IF(B13=E13,"Invalid: self-coach",IF(G13<>"active","Invalid: coach inactive",IF(D13=E13,"Invalid: already assigned",IF(I13="At capacity","Invalid: at capacity","OK"))))))
C14: =IF(B14="","",IFERROR(INDEX(Employees!$B$5:$B$200,MATCH(B14,Employees!$A$5:$A$200,0)),"ID not found")) | D14: =IF(B14="","",IFERROR(INDEX(Employees!$J$5:$J$200,MATCH(B14,Employees!$A$5:$A$200,0))&"","ID not found")) | F14: =IF(E14="","",IFERROR(INDEX(Employees!$B$5:$B$200,MATCH(E14,Employees!$A$5:$A$200,0)),"ID not found")) | G14: =IF(E14="","",IFERROR(INDEX(Employees!$I$5:$I$200,MATCH(E14,Employees!$A$5:$A$200,0)),"not found")) | H14: =IF(E14="","",COUNTIF(Employees!$J$5:$J$200,E14)) | I14: =IF(E14="","",IF(H14>=Lists!$E$10,"At capacity","OK")) | J14: =IF(B14="","",IF(G14="not found","Invalid: coach ID not found",IF(B14=E14,"Invalid: self-coach",IF(G14<>"active","Invalid: coach inactive",IF(D14=E14,"Invalid: already assigned",IF(I14="At capacity","Invalid: at capacity","OK"))))))
C15: =IF(B15="","",IFERROR(INDEX(Employees!$B$5:$B$200,MATCH(B15,Employees!$A$5:$A$200,0)),"ID not found")) | D15: =IF(B15="","",IFERROR(INDEX(Employees!$J$5:$J$200,MATCH(B15,Employees!$A$5:$A$200,0))&"","ID not found")) | F15: =IF(E15="","",IFERROR(INDEX(Employees!$B$5:$B$200,MATCH(E15,Employees!$A$5:$A$200,0)),"ID not found")) | G15: =IF(E15="","",IFERROR(INDEX(Employees!$I$5:$I$200,MATCH(E15,Employees!$A$5:$A$200,0)),"not found")) | H15: =IF(E15="","",COUNTIF(Employees!$J$5:$J$200,E15)) | I15: =IF(E15="","",IF(H15>=Lists!$E$10,"At capacity","OK")) | J15: =IF(B15="","",IF(G15="not found","Invalid: coach ID not found",IF(B15=E15,"Invalid: self-coach",IF(G15<>"active","Invalid: coach inactive",IF(D15=E15,"Invalid: already assigned",IF(I15="At capacity","Invalid: at capacity","OK"))))))
C16: =IF(B16="","",IFERROR(INDEX(Employees!$B$5:$B$200,MATCH(B16,Employees!$A$5:$A$200,0)),"ID not found")) | D16: =IF(B16="","",IFERROR(INDEX(Employees!$J$5:$J$200,MATCH(B16,Employees!$A$5:$A$200,0))&"","ID not found")) | F16: =IF(E16="","",IFERROR(INDEX(Employees!$B$5:$B$200,MATCH(E16,Employees!$A$5:$A$200,0)),"ID not found")) | G16: =IF(E16="","",IFERROR(INDEX(Employees!$I$5:$I$200,MATCH(E16,Employees!$A$5:$A$200,0)),"not found")) | H16: =IF(E16="","",COUNTIF(Employees!$J$5:$J$200,E16)) | I16: =IF(E16="","",IF(H16>=Lists!$E$10,"At capacity","OK")) | J16: =IF(B16="","",IF(G16="not found","Invalid: coach ID not found",IF(B16=E16,"Invalid: self-coach",IF(G16<>"active","Invalid: coach inactive",IF(D16=E16,"Invalid: already assigned",IF(I16="At capacity","Invalid: at capacity","OK"))))))
C17: =IF(B17="","",IFERROR(INDEX(Employees!$B$5:$B$200,MATCH(B17,Employees!$A$5:$A$200,0)),"ID not found")) | D17: =IF(B17="","",IFERROR(INDEX(Employees!$J$5:$J$200,MATCH(B17,Employees!$A$5:$A$200,0))&"","ID not found")) | F17: =IF(E17="","",IFERROR(INDEX(Employees!$B$5:$B$200,MATCH(E17,Employees!$A$5:$A$200,0)),"ID not found")) | G17: =IF(E17="","",IFERROR(INDEX(Employees!$I$5:$I$200,MATCH(E17,Employees!$A$5:$A$200,0)),"not found")) | H17: =IF(E17="","",COUNTIF(Employees!$J$5:$J$200,E17)) | I17: =IF(E17="","",IF(H17>=Lists!$E$10,"At capacity","OK")) | J17: =IF(B17="","",IF(G17="not found","Invalid: coach ID not found",IF(B17=E17,"Invalid: self-coach",IF(G17<>"active","Invalid: coach inactive",IF(D17=E17,"Invalid: already assigned",IF(I17="At capacity","Invalid: at capacity","OK"))))))
C18: =IF(B18="","",IFERROR(INDEX(Employees!$B$5:$B$200,MATCH(B18,Employees!$A$5:$A$200,0)),"ID not found")) | D18: =IF(B18="","",IFERROR(INDEX(Employees!$J$5:$J$200,MATCH(B18,Employees!$A$5:$A$200,0))&"","ID not found")) | F18: =IF(E18="","",IFERROR(INDEX(Employees!$B$5:$B$200,MATCH(E18,Employees!$A$5:$A$200,0)),"ID not found")) | G18: =IF(E18="","",IFERROR(INDEX(Employees!$I$5:$I$200,MATCH(E18,Employees!$A$5:$A$200,0)),"not found")) | H18: =IF(E18="","",COUNTIF(Employees!$J$5:$J$200,E18)) | I18: =IF(E18="","",IF(H18>=Lists!$E$10,"At capacity","OK")) | J18: =IF(B18="","",IF(G18="not found","Invalid: coach ID not found",IF(B18=E18,"Invalid: self-coach",IF(G18<>"active","Invalid: coach inactive",IF(D18=E18,"Invalid: already assigned",IF(I18="At capacity","Invalid: at capacity","OK"))))))
... C104: =IF(B104="","",IFERROR(INDEX(Employees!$B$5:$B$200,MATCH(B104,Employees!$A$5:$A$200,0)),"ID not found")) | D104: =IF(B104="","",IFERROR(INDEX(Employees!$J$5:$J$200,MATCH(B104,Employees!$A$5:$A$200,0))&"","ID not found")) | F104: =IF(E104="","",IFERROR(INDEX(Employees!$B$5:$B$200,MATCH(E104,Employees!$A$5:$A$200,0)),"ID not found")) | G104: =IF(E104="","",IFERROR(INDEX(Employees!$I$5:$I$200,MATCH(E104,Employees!$A$5:$A$200,0)),"not found")) | H104: =IF(E104="","",COUNTIF(Employees!$J$5:$J$200,E104)) | I104: =IF(E104="","",IF(H104>=Lists!$E$10,"At capacity","OK")) | J104: =IF(B104="","",IF(G104="not found","Invalid: coach ID not found",IF(B104=E104,"Invalid: self-coach",IF(G104<>"active","Invalid: coach inactive",IF(D104=E104,"Invalid: already assigned",IF(I104="At capacity","Invalid: at capacity","OK"))))))

Sheet Bike_to_Work
A1: Bike to Work Scheme
A2: Caps and gap come from Lists (assumptions - verify against policy). SAMPLE rows 5-6.
A4: Date Applied | B4: Emp ID | C4: Employee Name | D4: Employment Status | E4: Item Type | F4: Cost (EUR) | G4: Cap (EUR) | H4: Within Cap? | I4: Previous Claim Date | J4: Eligibility | K4: Status | L4: Notes
A5: 46288 | B5: E1003 | C5: =IF(B5="","",IFERROR(INDEX(Employees!$B$5:$B$200,MATCH(B5,Employees!$A$5:$A$200,0)),"ID not found")) -> Niamh Byrne | D5: =IF(B5="","",IFERROR(INDEX(Employees!$I$5:$I$200,MATCH(B5,Employees!$A$5:$A$200,0)),"not found")) -> active | E5: E-bike | F5: 1400 | G5: =IF(E5="","",IF(E5="E-bike",Lists!$E$6,Lists!$E$5)) -> 1500 | H5: =IF(OR(F5="",G5=""),"",IF(AND(F5>0,F5<=G5),"Yes","No - exceeds cap")) -> Yes | J5: =IF(B5="","",IF(H5="","Incomplete",IF(D5<>"active","Not eligible: not active",IF(H5<>"Yes","Not eligible: cost",IF(I5="","Eligible",IF(EDATE(I5,12*Lists!$E$7)<=A5,"Eligible","Not eligible: prior claim")))))) -> Eligible | K5: Approved | L5: Sample
A6: 46296 | B6: E1005 | C6: =IF(B6="","",IFERROR(INDEX(Employees!$B$5:$B$200,MATCH(B6,Employees!$A$5:$A$200,0)),"ID not found")) -> Ciara Kelly | D6: =IF(B6="","",IFERROR(INDEX(Employees!$I$5:$I$200,MATCH(B6,Employees!$A$5:$A$200,0)),"not found")) -> active | E6: Bike | F6: 950 | G6: =IF(E6="","",IF(E6="E-bike",Lists!$E$6,Lists!$E$5)) -> 1500 | H6: =IF(OR(F6="",G6=""),"",IF(AND(F6>0,F6<=G6),"Yes","No - exceeds cap")) -> Yes | I6: 45422 | J6: =IF(B6="","",IF(H6="","Incomplete",IF(D6<>"active","Not eligible: not active",IF(H6<>"Yes","Not eligible: cost",IF(I6="","Eligible",IF(EDATE(I6,12*Lists!$E$7)<=A6,"Eligible","Not eligible: prior claim")))))) -> Not eligible: prior claim | K6: Pending | L6: Prior claim 2024 - should flag
C7: =IF(B7="","",IFERROR(INDEX(Employees!$B$5:$B$200,MATCH(B7,Employees!$A$5:$A$200,0)),"ID not found")) | D7: =IF(B7="","",IFERROR(INDEX(Employees!$I$5:$I$200,MATCH(B7,Employees!$A$5:$A$200,0)),"not found")) | G7: =IF(E7="","",IF(E7="E-bike",Lists!$E$6,Lists!$E$5)) | H7: =IF(OR(F7="",G7=""),"",IF(AND(F7>0,F7<=G7),"Yes","No - exceeds cap")) | J7: =IF(B7="","",IF(H7="","Incomplete",IF(D7<>"active","Not eligible: not active",IF(H7<>"Yes","Not eligible: cost",IF(I7="","Eligible",IF(EDATE(I7,12*Lists!$E$7)<=A7,"Eligible","Not eligible: prior claim"))))))
C8: =IF(B8="","",IFERROR(INDEX(Employees!$B$5:$B$200,MATCH(B8,Employees!$A$5:$A$200,0)),"ID not found")) | D8: =IF(B8="","",IFERROR(INDEX(Employees!$I$5:$I$200,MATCH(B8,Employees!$A$5:$A$200,0)),"not found")) | G8: =IF(E8="","",IF(E8="E-bike",Lists!$E$6,Lists!$E$5)) | H8: =IF(OR(F8="",G8=""),"",IF(AND(F8>0,F8<=G8),"Yes","No - exceeds cap")) | J8: =IF(B8="","",IF(H8="","Incomplete",IF(D8<>"active","Not eligible: not active",IF(H8<>"Yes","Not eligible: cost",IF(I8="","Eligible",IF(EDATE(I8,12*Lists!$E$7)<=A8,"Eligible","Not eligible: prior claim"))))))
C9: =IF(B9="","",IFERROR(INDEX(Employees!$B$5:$B$200,MATCH(B9,Employees!$A$5:$A$200,0)),"ID not found")) | D9: =IF(B9="","",IFERROR(INDEX(Employees!$I$5:$I$200,MATCH(B9,Employees!$A$5:$A$200,0)),"not found")) | G9: =IF(E9="","",IF(E9="E-bike",Lists!$E$6,Lists!$E$5)) | H9: =IF(OR(F9="",G9=""),"",IF(AND(F9>0,F9<=G9),"Yes","No - exceeds cap")) | J9: =IF(B9="","",IF(H9="","Incomplete",IF(D9<>"active","Not eligible: not active",IF(H9<>"Yes","Not eligible: cost",IF(I9="","Eligible",IF(EDATE(I9,12*Lists!$E$7)<=A9,"Eligible","Not eligible: prior claim"))))))
C10: =IF(B10="","",IFERROR(INDEX(Employees!$B$5:$B$200,MATCH(B10,Employees!$A$5:$A$200,0)),"ID not found")) | D10: =IF(B10="","",IFERROR(INDEX(Employees!$I$5:$I$200,MATCH(B10,Employees!$A$5:$A$200,0)),"not found")) | G10: =IF(E10="","",IF(E10="E-bike",Lists!$E$6,Lists!$E$5)) | H10: =IF(OR(F10="",G10=""),"",IF(AND(F10>0,F10<=G10),"Yes","No - exceeds cap")) | J10: =IF(B10="","",IF(H10="","Incomplete",IF(D10<>"active","Not eligible: not active",IF(H10<>"Yes","Not eligible: cost",IF(I10="","Eligible",IF(EDATE(I10,12*Lists!$E$7)<=A10,"Eligible","Not eligible: prior claim"))))))
C11: =IF(B11="","",IFERROR(INDEX(Employees!$B$5:$B$200,MATCH(B11,Employees!$A$5:$A$200,0)),"ID not found")) | D11: =IF(B11="","",IFERROR(INDEX(Employees!$I$5:$I$200,MATCH(B11,Employees!$A$5:$A$200,0)),"not found")) | G11: =IF(E11="","",IF(E11="E-bike",Lists!$E$6,Lists!$E$5)) | H11: =IF(OR(F11="",G11=""),"",IF(AND(F11>0,F11<=G11),"Yes","No - exceeds cap")) | J11: =IF(B11="","",IF(H11="","Incomplete",IF(D11<>"active","Not eligible: not active",IF(H11<>"Yes","Not eligible: cost",IF(I11="","Eligible",IF(EDATE(I11,12*Lists!$E$7)<=A11,"Eligible","Not eligible: prior claim"))))))
C12: =IF(B12="","",IFERROR(INDEX(Employees!$B$5:$B$200,MATCH(B12,Employees!$A$5:$A$200,0)),"ID not found")) | D12: =IF(B12="","",IFERROR(INDEX(Employees!$I$5:$I$200,MATCH(B12,Employees!$A$5:$A$200,0)),"not found")) | G12: =IF(E12="","",IF(E12="E-bike",Lists!$E$6,Lists!$E$5)) | H12: =IF(OR(F12="",G12=""),"",IF(AND(F12>0,F12<=G12),"Yes","No - exceeds cap")) | J12: =IF(B12="","",IF(H12="","Incomplete",IF(D12<>"active","Not eligible: not active",IF(H12<>"Yes","Not eligible: cost",IF(I12="","Eligible",IF(EDATE(I12,12*Lists!$E$7)<=A12,"Eligible","Not eligible: prior claim"))))))
C13: =IF(B13="","",IFERROR(INDEX(Employees!$B$5:$B$200,MATCH(B13,Employees!$A$5:$A$200,0)),"ID not found")) | D13: =IF(B13="","",IFERROR(INDEX(Employees!$I$5:$I$200,MATCH(B13,Employees!$A$5:$A$200,0)),"not found")) | G13: =IF(E13="","",IF(E13="E-bike",Lists!$E$6,Lists!$E$5)) | H13: =IF(OR(F13="",G13=""),"",IF(AND(F13>0,F13<=G13),"Yes","No - exceeds cap")) | J13: =IF(B13="","",IF(H13="","Incomplete",IF(D13<>"active","Not eligible: not active",IF(H13<>"Yes","Not eligible: cost",IF(I13="","Eligible",IF(EDATE(I13,12*Lists!$E$7)<=A13,"Eligible","Not eligible: prior claim"))))))
C14: =IF(B14="","",IFERROR(INDEX(Employees!$B$5:$B$200,MATCH(B14,Employees!$A$5:$A$200,0)),"ID not found")) | D14: =IF(B14="","",IFERROR(INDEX(Employees!$I$5:$I$200,MATCH(B14,Employees!$A$5:$A$200,0)),"not found")) | G14: =IF(E14="","",IF(E14="E-bike",Lists!$E$6,Lists!$E$5)) | H14: =IF(OR(F14="",G14=""),"",IF(AND(F14>0,F14<=G14),"Yes","No - exceeds cap")) | J14: =IF(B14="","",IF(H14="","Incomplete",IF(D14<>"active","Not eligible: not active",IF(H14<>"Yes","Not eligible: cost",IF(I14="","Eligible",IF(EDATE(I14,12*Lists!$E$7)<=A14,"Eligible","Not eligible: prior claim"))))))
C15: =IF(B15="","",IFERROR(INDEX(Employees!$B$5:$B$200,MATCH(B15,Employees!$A$5:$A$200,0)),"ID not found")) | D15: =IF(B15="","",IFERROR(INDEX(Employees!$I$5:$I$200,MATCH(B15,Employees!$A$5:$A$200,0)),"not found")) | G15: =IF(E15="","",IF(E15="E-bike",Lists!$E$6,Lists!$E$5)) | H15: =IF(OR(F15="",G15=""),"",IF(AND(F15>0,F15<=G15),"Yes","No - exceeds cap")) | J15: =IF(B15="","",IF(H15="","Incomplete",IF(D15<>"active","Not eligible: not active",IF(H15<>"Yes","Not eligible: cost",IF(I15="","Eligible",IF(EDATE(I15,12*Lists!$E$7)<=A15,"Eligible","Not eligible: prior claim"))))))
C16: =IF(B16="","",IFERROR(INDEX(Employees!$B$5:$B$200,MATCH(B16,Employees!$A$5:$A$200,0)),"ID not found")) | D16: =IF(B16="","",IFERROR(INDEX(Employees!$I$5:$I$200,MATCH(B16,Employees!$A$5:$A$200,0)),"not found")) | G16: =IF(E16="","",IF(E16="E-bike",Lists!$E$6,Lists!$E$5)) | H16: =IF(OR(F16="",G16=""),"",IF(AND(F16>0,F16<=G16),"Yes","No - exceeds cap")) | J16: =IF(B16="","",IF(H16="","Incomplete",IF(D16<>"active","Not eligible: not active",IF(H16<>"Yes","Not eligible: cost",IF(I16="","Eligible",IF(EDATE(I16,12*Lists!$E$7)<=A16,"Eligible","Not eligible: prior claim"))))))
C17: =IF(B17="","",IFERROR(INDEX(Employees!$B$5:$B$200,MATCH(B17,Employees!$A$5:$A$200,0)),"ID not found")) | D17: =IF(B17="","",IFERROR(INDEX(Employees!$I$5:$I$200,MATCH(B17,Employees!$A$5:$A$200,0)),"not found")) | G17: =IF(E17="","",IF(E17="E-bike",Lists!$E$6,Lists!$E$5)) | H17: =IF(OR(F17="",G17=""),"",IF(AND(F17>0,F17<=G17),"Yes","No - exceeds cap")) | J17: =IF(B17="","",IF(H17="","Incomplete",IF(D17<>"active","Not eligible: not active",IF(H17<>"Yes","Not eligible: cost",IF(I17="","Eligible",IF(EDATE(I17,12*Lists!$E$7)<=A17,"Eligible","Not eligible: prior claim"))))))
C18: =IF(B18="","",IFERROR(INDEX(Employees!$B$5:$B$200,MATCH(B18,Employees!$A$5:$A$200,0)),"ID not found")) | D18: =IF(B18="","",IFERROR(INDEX(Employees!$I$5:$I$200,MATCH(B18,Employees!$A$5:$A$200,0)),"not found")) | G18: =IF(E18="","",IF(E18="E-bike",Lists!$E$6,Lists!$E$5)) | H18: =IF(OR(F18="",G18=""),"",IF(AND(F18>0,F18<=G18),"Yes","No - exceeds cap")) | J18: =IF(B18="","",IF(H18="","Incomplete",IF(D18<>"active","Not eligible: not active",IF(H18<>"Yes","Not eligible: cost",IF(I18="","Eligible",IF(EDATE(I18,12*Lists!$E$7)<=A18,"Eligible","Not eligible: prior claim"))))))
... C104: =IF(B104="","",IFERROR(INDEX(Employees!$B$5:$B$200,MATCH(B104,Employees!$A$5:$A$200,0)),"ID not found")) | D104: =IF(B104="","",IFERROR(INDEX(Employees!$I$5:$I$200,MATCH(B104,Employees!$A$5:$A$200,0)),"not found")) | G104: =IF(E104="","",IF(E104="E-bike",Lists!$E$6,Lists!$E$5)) | H104: =IF(OR(F104="",G104=""),"",IF(AND(F104>0,F104<=G104),"Yes","No - exceeds cap")) | J104: =IF(B104="","",IF(H104="","Incomplete",IF(D104<>"active","Not eligible: not active",IF(H104<>"Yes","Not eligible: cost",IF(I104="","Eligible",IF(EDATE(I104,12*Lists!$E$7)<=A104,"Eligible","Not eligible: prior claim"))))))

Sheet Eyecare_VDU
A1: Eyecare / VDU Vouchers
A2: Eligibility: active + registered VDU user + gap since last voucher (Lists). SAMPLE rows 5-6.
A4: Date Requested | B4: Emp ID | C4: Employee Name | D4: VDU User? | E4: Employment Status | F4: Last Voucher Date | G4: Eligibility | H4: Voucher Code | I4: Expiry Date | J4: Status | K4: Notes
A5: 46289 | B5: E1001 | C5: =IF(B5="","",IFERROR(INDEX(Employees!$B$5:$B$200,MATCH(B5,Employees!$A$5:$A$200,0)),"ID not found")) -> Aoife Murphy | D5: =IF(B5="","",IFERROR(INDEX(Employees!$K$5:$K$200,MATCH(B5,Employees!$A$5:$A$200,0)),"not found")) -> Yes | E5: =IF(B5="","",IFERROR(INDEX(Employees!$I$5:$I$200,MATCH(B5,Employees!$A$5:$A$200,0)),"not found")) -> active | G5: =IF(B5="","",IF(E5<>"active","Not eligible: not active",IF(D5<>"Yes","Not eligible: not VDU user",IF(F5="","Eligible",IF(EDATE(F5,Lists!$E$8)<=A5,"Eligible","Not eligible: within gap period"))))) -> Eligible | H5: VDU-E1001-0924 | I5: =IF(OR(A5="",G5<>"Eligible"),"",A5+Lists!$E$9) -> 46379 | J5: Completed | K5: Sample
A6: 46295 | B6: E1007 | C6: =IF(B6="","",IFERROR(INDEX(Employees!$B$5:$B$200,MATCH(B6,Employees!$A$5:$A$200,0)),"ID not found")) -> Emma Ryan | D6: =IF(B6="","",IFERROR(INDEX(Employees!$K$5:$K$200,MATCH(B6,Employees!$A$5:$A$200,0)),"not found")) -> No | E6: =IF(B6="","",IFERROR(INDEX(Employees!$I$5:$I$200,MATCH(B6,Employees!$A$5:$A$200,0)),"not found")) -> active | G6: =IF(B6="","",IF(E6<>"active","Not eligible: not active",IF(D6<>"Yes","Not eligible: not VDU user",IF(F6="","Eligible",IF(EDATE(F6,Lists!$E$8)<=A6,"Eligible","Not eligible: within gap period"))))) -> Not eligible: not VDU user | I6: =IF(OR(A6="",G6<>"Eligible"),"",A6+Lists!$E$9) | J6: Pending | K6: Not a VDU user - should flag
C7: =IF(B7="","",IFERROR(INDEX(Employees!$B$5:$B$200,MATCH(B7,Employees!$A$5:$A$200,0)),"ID not found")) | D7: =IF(B7="","",IFERROR(INDEX(Employees!$K$5:$K$200,MATCH(B7,Employees!$A$5:$A$200,0)),"not found")) | E7: =IF(B7="","",IFERROR(INDEX(Employees!$I$5:$I$200,MATCH(B7,Employees!$A$5:$A$200,0)),"not found")) | G7: =IF(B7="","",IF(E7<>"active","Not eligible: not active",IF(D7<>"Yes","Not eligible: not VDU user",IF(F7="","Eligible",IF(EDATE(F7,Lists!$E$8)<=A7,"Eligible","Not eligible: within gap period"))))) | I7: =IF(OR(A7="",G7<>"Eligible"),"",A7+Lists!$E$9)
C8: =IF(B8="","",IFERROR(INDEX(Employees!$B$5:$B$200,MATCH(B8,Employees!$A$5:$A$200,0)),"ID not found")) | D8: =IF(B8="","",IFERROR(INDEX(Employees!$K$5:$K$200,MATCH(B8,Employees!$A$5:$A$200,0)),"not found")) | E8: =IF(B8="","",IFERROR(INDEX(Employees!$I$5:$I$200,MATCH(B8,Employees!$A$5:$A$200,0)),"not found")) | G8: =IF(B8="","",IF(E8<>"active","Not eligible: not active",IF(D8<>"Yes","Not eligible: not VDU user",IF(F8="","Eligible",IF(EDATE(F8,Lists!$E$8)<=A8,"Eligible","Not eligible: within gap period"))))) | I8: =IF(OR(A8="",G8<>"Eligible"),"",A8+Lists!$E$9)
C9: =IF(B9="","",IFERROR(INDEX(Employees!$B$5:$B$200,MATCH(B9,Employees!$A$5:$A$200,0)),"ID not found")) | D9: =IF(B9="","",IFERROR(INDEX(Employees!$K$5:$K$200,MATCH(B9,Employees!$A$5:$A$200,0)),"not found")) | E9: =IF(B9="","",IFERROR(INDEX(Employees!$I$5:$I$200,MATCH(B9,Employees!$A$5:$A$200,0)),"not found")) | G9: =IF(B9="","",IF(E9<>"active","Not eligible: not active",IF(D9<>"Yes","Not eligible: not VDU user",IF(F9="","Eligible",IF(EDATE(F9,Lists!$E$8)<=A9,"Eligible","Not eligible: within gap period"))))) | I9: =IF(OR(A9="",G9<>"Eligible"),"",A9+Lists!$E$9)
C10: =IF(B10="","",IFERROR(INDEX(Employees!$B$5:$B$200,MATCH(B10,Employees!$A$5:$A$200,0)),"ID not found")) | D10: =IF(B10="","",IFERROR(INDEX(Employees!$K$5:$K$200,MATCH(B10,Employees!$A$5:$A$200,0)),"not found")) | E10: =IF(B10="","",IFERROR(INDEX(Employees!$I$5:$I$200,MATCH(B10,Employees!$A$5:$A$200,0)),"not found")) | G10: =IF(B10="","",IF(E10<>"active","Not eligible: not active",IF(D10<>"Yes","Not eligible: not VDU user",IF(F10="","Eligible",IF(EDATE(F10,Lists!$E$8)<=A10,"Eligible","Not eligible: within gap period"))))) | I10: =IF(OR(A10="",G10<>"Eligible"),"",A10+Lists!$E$9)
C11: =IF(B11="","",IFERROR(INDEX(Employees!$B$5:$B$200,MATCH(B11,Employees!$A$5:$A$200,0)),"ID not found")) | D11: =IF(B11="","",IFERROR(INDEX(Employees!$K$5:$K$200,MATCH(B11,Employees!$A$5:$A$200,0)),"not found")) | E11: =IF(B11="","",IFERROR(INDEX(Employees!$I$5:$I$200,MATCH(B11,Employees!$A$5:$A$200,0)),"not found")) | G11: =IF(B11="","",IF(E11<>"active","Not eligible: not active",IF(D11<>"Yes","Not eligible: not VDU user",IF(F11="","Eligible",IF(EDATE(F11,Lists!$E$8)<=A11,"Eligible","Not eligible: within gap period"))))) | I11: =IF(OR(A11="",G11<>"Eligible"),"",A11+Lists!$E$9)
C12: =IF(B12="","",IFERROR(INDEX(Employees!$B$5:$B$200,MATCH(B12,Employees!$A$5:$A$200,0)),"ID not found")) | D12: =IF(B12="","",IFERROR(INDEX(Employees!$K$5:$K$200,MATCH(B12,Employees!$A$5:$A$200,0)),"not found")) | E12: =IF(B12="","",IFERROR(INDEX(Employees!$I$5:$I$200,MATCH(B12,Employees!$A$5:$A$200,0)),"not found")) | G12: =IF(B12="","",IF(E12<>"active","Not eligible: not active",IF(D12<>"Yes","Not eligible: not VDU user",IF(F12="","Eligible",IF(EDATE(F12,Lists!$E$8)<=A12,"Eligible","Not eligible: within gap period"))))) | I12: =IF(OR(A12="",G12<>"Eligible"),"",A12+Lists!$E$9)
C13: =IF(B13="","",IFERROR(INDEX(Employees!$B$5:$B$200,MATCH(B13,Employees!$A$5:$A$200,0)),"ID not found")) | D13: =IF(B13="","",IFERROR(INDEX(Employees!$K$5:$K$200,MATCH(B13,Employees!$A$5:$A$200,0)),"not found")) | E13: =IF(B13="","",IFERROR(INDEX(Employees!$I$5:$I$200,MATCH(B13,Employees!$A$5:$A$200,0)),"not found")) | G13: =IF(B13="","",IF(E13<>"active","Not eligible: not active",IF(D13<>"Yes","Not eligible: not VDU user",IF(F13="","Eligible",IF(EDATE(F13,Lists!$E$8)<=A13,"Eligible","Not eligible: within gap period"))))) | I13: =IF(OR(A13="",G13<>"Eligible"),"",A13+Lists!$E$9)
C14: =IF(B14="","",IFERROR(INDEX(Employees!$B$5:$B$200,MATCH(B14,Employees!$A$5:$A$200,0)),"ID not found")) | D14: =IF(B14="","",IFERROR(INDEX(Employees!$K$5:$K$200,MATCH(B14,Employees!$A$5:$A$200,0)),"not found")) | E14: =IF(B14="","",IFERROR(INDEX(Employees!$I$5:$I$200,MATCH(B14,Employees!$A$5:$A$200,0)),"not found")) | G14: =IF(B14="","",IF(E14<>"active","Not eligible: not active",IF(D14<>"Yes","Not eligible: not VDU user",IF(F14="","Eligible",IF(EDATE(F14,Lists!$E$8)<=A14,"Eligible","Not eligible: within gap period"))))) | I14: =IF(OR(A14="",G14<>"Eligible"),"",A14+Lists!$E$9)
C15: =IF(B15="","",IFERROR(INDEX(Employees!$B$5:$B$200,MATCH(B15,Employees!$A$5:$A$200,0)),"ID not found")) | D15: =IF(B15="","",IFERROR(INDEX(Employees!$K$5:$K$200,MATCH(B15,Employees!$A$5:$A$200,0)),"not found")) | E15: =IF(B15="","",IFERROR(INDEX(Employees!$I$5:$I$200,MATCH(B15,Employees!$A$5:$A$200,0)),"not found")) | G15: =IF(B15="","",IF(E15<>"active","Not eligible: not active",IF(D15<>"Yes","Not eligible: not VDU user",IF(F15="","Eligible",IF(EDATE(F15,Lists!$E$8)<=A15,"Eligible","Not eligible: within gap period"))))) | I15: =IF(OR(A15="",G15<>"Eligible"),"",A15+Lists!$E$9)
C16: =IF(B16="","",IFERROR(INDEX(Employees!$B$5:$B$200,MATCH(B16,Employees!$A$5:$A$200,0)),"ID not found")) | D16: =IF(B16="","",IFERROR(INDEX(Employees!$K$5:$K$200,MATCH(B16,Employees!$A$5:$A$200,0)),"not found")) | E16: =IF(B16="","",IFERROR(INDEX(Employees!$I$5:$I$200,MATCH(B16,Employees!$A$5:$A$200,0)),"not found")) | G16: =IF(B16="","",IF(E16<>"active","Not eligible: not active",IF(D16<>"Yes","Not eligible: not VDU user",IF(F16="","Eligible",IF(EDATE(F16,Lists!$E$8)<=A16,"Eligible","Not eligible: within gap period"))))) | I16: =IF(OR(A16="",G16<>"Eligible"),"",A16+Lists!$E$9)
C17: =IF(B17="","",IFERROR(INDEX(Employees!$B$5:$B$200,MATCH(B17,Employees!$A$5:$A$200,0)),"ID not found")) | D17: =IF(B17="","",IFERROR(INDEX(Employees!$K$5:$K$200,MATCH(B17,Employees!$A$5:$A$200,0)),"not found")) | E17: =IF(B17="","",IFERROR(INDEX(Employees!$I$5:$I$200,MATCH(B17,Employees!$A$5:$A$200,0)),"not found")) | G17: =IF(B17="","",IF(E17<>"active","Not eligible: not active",IF(D17<>"Yes","Not eligible: not VDU user",IF(F17="","Eligible",IF(EDATE(F17,Lists!$E$8)<=A17,"Eligible","Not eligible: within gap period"))))) | I17: =IF(OR(A17="",G17<>"Eligible"),"",A17+Lists!$E$9)
C18: =IF(B18="","",IFERROR(INDEX(Employees!$B$5:$B$200,MATCH(B18,Employees!$A$5:$A$200,0)),"ID not found")) | D18: =IF(B18="","",IFERROR(INDEX(Employees!$K$5:$K$200,MATCH(B18,Employees!$A$5:$A$200,0)),"not found")) | E18: =IF(B18="","",IFERROR(INDEX(Employees!$I$5:$I$200,MATCH(B18,Employees!$A$5:$A$200,0)),"not found")) | G18: =IF(B18="","",IF(E18<>"active","Not eligible: not active",IF(D18<>"Yes","Not eligible: not VDU user",IF(F18="","Eligible",IF(EDATE(F18,Lists!$E$8)<=A18,"Eligible","Not eligible: within gap period"))))) | I18: =IF(OR(A18="",G18<>"Eligible"),"",A18+Lists!$E$9)
... C104: =IF(B104="","",IFERROR(INDEX(Employees!$B$5:$B$200,MATCH(B104,Employees!$A$5:$A$200,0)),"ID not found")) | D104: =IF(B104="","",IFERROR(INDEX(Employees!$K$5:$K$200,MATCH(B104,Employees!$A$5:$A$200,0)),"not found")) | E104: =IF(B104="","",IFERROR(INDEX(Employees!$I$5:$I$200,MATCH(B104,Employees!$A$5:$A$200,0)),"not found")) | G104: =IF(B104="","",IF(E104<>"active","Not eligible: not active",IF(D104<>"Yes","Not eligible: not VDU user",IF(F104="","Eligible",IF(EDATE(F104,Lists!$E$8)<=A104,"Eligible","Not eligible: within gap period"))))) | I104: =IF(OR(A104="",G104<>"Eligible"),"",A104+Lists!$E$9)

Sheet Milestones
A1: Personal Milestones (Perx / Flowers / Baby Gifts)
A2: Gift and value look up from Lists. SAMPLE rows 5-6.
A4: Event Date | B4: Emp ID | C4: Employee Name | D4: Event | E4: Gift Type | F4: Value (EUR) | G4: Delivery Details Verified? | H4: Dispatched Date | I4: Status | J4: Personal Message | K4: Notes
A5: 46290 | B5: E1002 | C5: =IF(B5="","",IFERROR(INDEX(Employees!$B$5:$B$200,MATCH(B5,Employees!$A$5:$A$200,0)),"ID not found")) -> Conor Walsh | D5: Baby | E5: =IF(D5="","",IFERROR(INDEX(Lists!$I$4:$I$8,MATCH(D5,Lists!$H$4:$H$8,0)),"")) -> Baby gift hamper | F5: =IF(D5="","",IFERROR(INDEX(Lists!$J$4:$J$8,MATCH(D5,Lists!$H$4:$H$8,0)),"")) -> 75 | G5: Yes | H5: 46294 | I5: Completed | J5: Congratulations on the new arrival!
A6: 46296 | B6: E1006 | C6: =IF(B6="","",IFERROR(INDEX(Employees!$B$5:$B$200,MATCH(B6,Employees!$A$5:$A$200,0)),"ID not found")) -> Liam O'Brien | D6: Long service | E6: =IF(D6="","",IFERROR(INDEX(Lists!$I$4:$I$8,MATCH(D6,Lists!$H$4:$H$8,0)),"")) -> Perx voucher | F6: =IF(D6="","",IFERROR(INDEX(Lists!$J$4:$J$8,MATCH(D6,Lists!$H$4:$H$8,0)),"")) -> 150 | G6: No | I6: Pending | J6: Thank you for 16 years of service.
C7: =IF(B7="","",IFERROR(INDEX(Employees!$B$5:$B$200,MATCH(B7,Employees!$A$5:$A$200,0)),"ID not found")) | E7: =IF(D7="","",IFERROR(INDEX(Lists!$I$4:$I$8,MATCH(D7,Lists!$H$4:$H$8,0)),"")) | F7: =IF(D7="","",IFERROR(INDEX(Lists!$J$4:$J$8,MATCH(D7,Lists!$H$4:$H$8,0)),""))
C8: =IF(B8="","",IFERROR(INDEX(Employees!$B$5:$B$200,MATCH(B8,Employees!$A$5:$A$200,0)),"ID not found")) | E8: =IF(D8="","",IFERROR(INDEX(Lists!$I$4:$I$8,MATCH(D8,Lists!$H$4:$H$8,0)),"")) | F8: =IF(D8="","",IFERROR(INDEX(Lists!$J$4:$J$8,MATCH(D8,Lists!$H$4:$H$8,0)),""))
C9: =IF(B9="","",IFERROR(INDEX(Employees!$B$5:$B$200,MATCH(B9,Employees!$A$5:$A$200,0)),"ID not found")) | E9: =IF(D9="","",IFERROR(INDEX(Lists!$I$4:$I$8,MATCH(D9,Lists!$H$4:$H$8,0)),"")) | F9: =IF(D9="","",IFERROR(INDEX(Lists!$J$4:$J$8,MATCH(D9,Lists!$H$4:$H$8,0)),""))
C10: =IF(B10="","",IFERROR(INDEX(Employees!$B$5:$B$200,MATCH(B10,Employees!$A$5:$A$200,0)),"ID not found")) | E10: =IF(D10="","",IFERROR(INDEX(Lists!$I$4:$I$8,MATCH(D10,Lists!$H$4:$H$8,0)),"")) | F10: =IF(D10="","",IFERROR(INDEX(Lists!$J$4:$J$8,MATCH(D10,Lists!$H$4:$H$8,0)),""))
C11: =IF(B11="","",IFERROR(INDEX(Employees!$B$5:$B$200,MATCH(B11,Employees!$A$5:$A$200,0)),"ID not found")) | E11: =IF(D11="","",IFERROR(INDEX(Lists!$I$4:$I$8,MATCH(D11,Lists!$H$4:$H$8,0)),"")) | F11: =IF(D11="","",IFERROR(INDEX(Lists!$J$4:$J$8,MATCH(D11,Lists!$H$4:$H$8,0)),""))
C12: =IF(B12="","",IFERROR(INDEX(Employees!$B$5:$B$200,MATCH(B12,Employees!$A$5:$A$200,0)),"ID not found")) | E12: =IF(D12="","",IFERROR(INDEX(Lists!$I$4:$I$8,MATCH(D12,Lists!$H$4:$H$8,0)),"")) | F12: =IF(D12="","",IFERROR(INDEX(Lists!$J$4:$J$8,MATCH(D12,Lists!$H$4:$H$8,0)),""))
C13: =IF(B13="","",IFERROR(INDEX(Employees!$B$5:$B$200,MATCH(B13,Employees!$A$5:$A$200,0)),"ID not found")) | E13: =IF(D13="","",IFERROR(INDEX(Lists!$I$4:$I$8,MATCH(D13,Lists!$H$4:$H$8,0)),"")) | F13: =IF(D13="","",IFERROR(INDEX(Lists!$J$4:$J$8,MATCH(D13,Lists!$H$4:$H$8,0)),""))
C14: =IF(B14="","",IFERROR(INDEX(Employees!$B$5:$B$200,MATCH(B14,Employees!$A$5:$A$200,0)),"ID not found")) | E14: =IF(D14="","",IFERROR(INDEX(Lists!$I$4:$I$8,MATCH(D14,Lists!$H$4:$H$8,0)),"")) | F14: =IF(D14="","",IFERROR(INDEX(Lists!$J$4:$J$8,MATCH(D14,Lists!$H$4:$H$8,0)),""))
C15: =IF(B15="","",IFERROR(INDEX(Employees!$B$5:$B$200,MATCH(B15,Employees!$A$5:$A$200,0)),"ID not found")) | E15: =IF(D15="","",IFERROR(INDEX(Lists!$I$4:$I$8,MATCH(D15,Lists!$H$4:$H$8,0)),"")) | F15: =IF(D15="","",IFERROR(INDEX(Lists!$J$4:$J$8,MATCH(D15,Lists!$H$4:$H$8,0)),""))
C16: =IF(B16="","",IFERROR(INDEX(Employees!$B$5:$B$200,MATCH(B16,Employees!$A$5:$A$200,0)),"ID not found")) | E16: =IF(D16="","",IFERROR(INDEX(Lists!$I$4:$I$8,MATCH(D16,Lists!$H$4:$H$8,0)),"")) | F16: =IF(D16="","",IFERROR(INDEX(Lists!$J$4:$J$8,MATCH(D16,Lists!$H$4:$H$8,0)),""))
C17: =IF(B17="","",IFERROR(INDEX(Employees!$B$5:$B$200,MATCH(B17,Employees!$A$5:$A$200,0)),"ID not found")) | E17: =IF(D17="","",IFERROR(INDEX(Lists!$I$4:$I$8,MATCH(D17,Lists!$H$4:$H$8,0)),"")) | F17: =IF(D17="","",IFERROR(INDEX(Lists!$J$4:$J$8,MATCH(D17,Lists!$H$4:$H$8,0)),""))
C18: =IF(B18="","",IFERROR(INDEX(Employees!$B$5:$B$200,MATCH(B18,Employees!$A$5:$A$200,0)),"ID not found")) | E18: =IF(D18="","",IFERROR(INDEX(Lists!$I$4:$I$8,MATCH(D18,Lists!$H$4:$H$8,0)),"")) | F18: =IF(D18="","",IFERROR(INDEX(Lists!$J$4:$J$8,MATCH(D18,Lists!$H$4:$H$8,0)),""))
... C104: =IF(B104="","",IFERROR(INDEX(Employees!$B$5:$B$200,MATCH(B104,Employees!$A$5:$A$200,0)),"ID not found")) | E104: =IF(D104="","",IFERROR(INDEX(Lists!$I$4:$I$8,MATCH(D104,Lists!$H$4:$H$8,0)),"")) | F104: =IF(D104="","",IFERROR(INDEX(Lists!$J$4:$J$8,MATCH(D104,Lists!$H$4:$H$8,0)),""))

Sheet Quality_Log
A1: Quality Log (four-eyes checks)
A2: Log every pre-release check. Fail + 'Wrong recipient' = possible personal-data breach -> escalate at once. SAMPLE rows 5-16.
A4: Date Checked | B4: Req ID | C4: Request Type | D4: Checker | E4: Result | F4: Error Category | G4: Corrected Before Release? | H4: Escalation / Action | I4: Notes
A5: 46286 | B5: REQ-0001 | C5: =IF(B5="","",IFERROR(INDEX(Request_Tracker!$B$6:$B$205,MATCH(B5,Request_Tracker!$A$6:$A$205,0)),"Req ID not found")) -> Salary Certificate | D5: Agent 2 | E5: Pass | H5: =IF(E5<>"Fail","",IF(F5="Wrong recipient","ESCALATE: possible personal data breach - notify Team Lead / DPO immediately",IF(G5="No","Escalate to Team Lead - error not corrected","Logged - corrected before release")))
A6: 46287 | B6: REQ-0002 | C6: =IF(B6="","",IFERROR(INDEX(Request_Tracker!$B$6:$B$205,MATCH(B6,Request_Tracker!$A$6:$A$205,0)),"Req ID not found")) -> Reference Letter | D6: Agent 1 | E6: Pass | H6: =IF(E6<>"Fail","",IF(F6="Wrong recipient","ESCALATE: possible personal data breach - notify Team Lead / DPO immediately",IF(G6="No","Escalate to Team Lead - error not corrected","Logged - corrected before release")))
A7: 46293 | B7: REQ-0003 | C7: =IF(B7="","",IFERROR(INDEX(Request_Tracker!$B$6:$B$205,MATCH(B7,Request_Tracker!$A$6:$A$205,0)),"Req ID not found")) -> Coach Change | D7: Agent 2 | E7: Pass | H7: =IF(E7<>"Fail","",IF(F7="Wrong recipient","ESCALATE: possible personal data breach - notify Team Lead / DPO immediately",IF(G7="No","Escalate to Team Lead - error not corrected","Logged - corrected before release")))
A8: 46290 | B8: REQ-0005 | C8: =IF(B8="","",IFERROR(INDEX(Request_Tracker!$B$6:$B$205,MATCH(B8,Request_Tracker!$A$6:$A$205,0)),"Req ID not found")) -> Eyecare / VDU Voucher | D8: Agent 2 | E8: Pass | H8: =IF(E8<>"Fail","",IF(F8="Wrong recipient","ESCALATE: possible personal data breach - notify Team Lead / DPO immediately",IF(G8="No","Escalate to Team Lead - error not corrected","Logged - corrected before release")))
A9: 46294 | B9: REQ-0006 | C9: =IF(B9="","",IFERROR(INDEX(Request_Tracker!$B$6:$B$205,MATCH(B9,Request_Tracker!$A$6:$A$205,0)),"Req ID not found")) -> Personal Milestone | D9: Agent 1 | E9: Pass | H9: =IF(E9<>"Fail","",IF(F9="Wrong recipient","ESCALATE: possible personal data breach - notify Team Lead / DPO immediately",IF(G9="No","Escalate to Team Lead - error not corrected","Logged - corrected before release")))
A10: 46294 | B10: REQ-0004 | C10: =IF(B10="","",IFERROR(INDEX(Request_Tracker!$B$6:$B$205,MATCH(B10,Request_Tracker!$A$6:$A$205,0)),"Req ID not found")) -> Bike to Work | D10: Agent 1 | E10: Fail | F10: Wrong recipient | G10: No | H10: =IF(E10<>"Fail","",IF(F10="Wrong recipient","ESCALATE: possible personal data breach - notify Team Lead / DPO immediately",IF(G10="No","Escalate to Team Lead - error not corrected","Logged - corrected before release"))) -> ESCALATE: possible personal data breach - notify Team Lead / DPO immediately | I10: SAMPLE incident - demonstrates the breach escalation rule
A11: 46295 | B11: REQ-0007 | C11: =IF(B11="","",IFERROR(INDEX(Request_Tracker!$B$6:$B$205,MATCH(B11,Request_Tracker!$A$6:$A$205,0)),"Req ID not found")) -> Salary Certificate | D11: Agent 2 | E11: Fail | F11: Wrong salary figure | G11: Yes | H11: =IF(E11<>"Fail","",IF(F11="Wrong recipient","ESCALATE: possible personal data breach - notify Team Lead / DPO immediately",IF(G11="No","Escalate to Team Lead - error not corrected","Logged - corrected before release"))) -> Logged - corrected before release | I11: Typo caught at four-eyes check before sending
A12: 46296 | B12: REQ-0008 | C12: =IF(B12="","",IFERROR(INDEX(Request_Tracker!$B$6:$B$205,MATCH(B12,Request_Tracker!$A$6:$A$205,0)),"Req ID not found")) -> Reference Letter | D12: Agent 1 | E12: Pass | H12: =IF(E12<>"Fail","",IF(F12="Wrong recipient","ESCALATE: possible personal data breach - notify Team Lead / DPO immediately",IF(G12="No","Escalate to Team Lead - error not corrected","Logged - corrected before release")))
A13: 46296 | B13: REQ-0009 | C13: =IF(B13="","",IFERROR(INDEX(Request_Tracker!$B$6:$B$205,MATCH(B13,Request_Tracker!$A$6:$A$205,0)),"Req ID not found")) -> Reference Letter | D13: Agent 2 | E13: Pass | H13: =IF(E13<>"Fail","",IF(F13="Wrong recipient","ESCALATE: possible personal data breach - notify Team Lead / DPO immediately",IF(G13="No","Escalate to Team Lead - error not corrected","Logged - corrected before release")))
A14: 46296 | B14: REQ-0010 | C14: =IF(B14="","",IFERROR(INDEX(Request_Tracker!$B$6:$B$205,MATCH(B14,Request_Tracker!$A$6:$A$205,0)),"Req ID not found")) -> Coach Change | D14: Agent 1 | E14: Pass | H14: =IF(E14<>"Fail","",IF(F14="Wrong recipient","ESCALATE: possible personal data breach - notify Team Lead / DPO immediately",IF(G14="No","Escalate to Team Lead - error not corrected","Logged - corrected before release")))
A15: 46297 | B15: REQ-0011 | C15: =IF(B15="","",IFERROR(INDEX(Request_Tracker!$B$6:$B$205,MATCH(B15,Request_Tracker!$A$6:$A$205,0)),"Req ID not found")) -> Bike to Work | D15: Agent 2 | E15: Pass | H15: =IF(E15<>"Fail","",IF(F15="Wrong recipient","ESCALATE: possible personal data breach - notify Team Lead / DPO immediately",IF(G15="No","Escalate to Team Lead - error not corrected","Logged - corrected before release")))
A16: 46297 | B16: REQ-0012 | C16: =IF(B16="","",IFERROR(INDEX(Request_Tracker!$B$6:$B$205,MATCH(B16,Request_Tracker!$A$6:$A$205,0)),"Req ID not found")) -> Salary Certificate | D16: Agent 1 | E16: Pass | H16: =IF(E16<>"Fail","",IF(F16="Wrong recipient","ESCALATE: possible personal data breach - notify Team Lead / DPO immediately",IF(G16="No","Escalate to Team Lead - error not corrected","Logged - corrected before release")))
C17: =IF(B17="","",IFERROR(INDEX(Request_Tracker!$B$6:$B$205,MATCH(B17,Request_Tracker!$A$6:$A$205,0)),"Req ID not found")) | H17: =IF(E17<>"Fail","",IF(F17="Wrong recipient","ESCALATE: possible personal data breach - notify Team Lead / DPO immediately",IF(G17="No","Escalate to Team Lead - error not corrected","Logged - corrected before release")))
C18: =IF(B18="","",IFERROR(INDEX(Request_Tracker!$B$6:$B$205,MATCH(B18,Request_Tracker!$A$6:$A$205,0)),"Req ID not found")) | H18: =IF(E18<>"Fail","",IF(F18="Wrong recipient","ESCALATE: possible personal data breach - notify Team Lead / DPO immediately",IF(G18="No","Escalate to Team Lead - error not corrected","Logged - corrected before release")))
C19: =IF(B19="","",IFERROR(INDEX(Request_Tracker!$B$6:$B$205,MATCH(B19,Request_Tracker!$A$6:$A$205,0)),"Req ID not found")) | H19: =IF(E19<>"Fail","",IF(F19="Wrong recipient","ESCALATE: possible personal data breach - notify Team Lead / DPO immediately",IF(G19="No","Escalate to Team Lead - error not corrected","Logged - corrected before release")))
C20: =IF(B20="","",IFERROR(INDEX(Request_Tracker!$B$6:$B$205,MATCH(B20,Request_Tracker!$A$6:$A$205,0)),"Req ID not found")) | H20: =IF(E20<>"Fail","",IF(F20="Wrong recipient","ESCALATE: possible personal data breach - notify Team Lead / DPO immediately",IF(G20="No","Escalate to Team Lead - error not corrected","Logged - corrected before release")))
C21: =IF(B21="","",IFERROR(INDEX(Request_Tracker!$B$6:$B$205,MATCH(B21,Request_Tracker!$A$6:$A$205,0)),"Req ID not found")) | H21: =IF(E21<>"Fail","",IF(F21="Wrong recipient","ESCALATE: possible personal data breach - notify Team Lead / DPO immediately",IF(G21="No","Escalate to Team Lead - error not corrected","Logged - corrected before release")))
C22: =IF(B22="","",IFERROR(INDEX(Request_Tracker!$B$6:$B$205,MATCH(B22,Request_Tracker!$A$6:$A$205,0)),"Req ID not found")) | H22: =IF(E22<>"Fail","",IF(F22="Wrong recipient","ESCALATE: possible personal data breach - notify Team Lead / DPO immediately",IF(G22="No","Escalate to Team Lead - error not corrected","Logged - corrected before release")))
C23: =IF(B23="","",IFERROR(INDEX(Request_Tracker!$B$6:$B$205,MATCH(B23,Request_Tracker!$A$6:$A$205,0)),"Req ID not found")) | H23: =IF(E23<>"Fail","",IF(F23="Wrong recipient","ESCALATE: possible personal data breach - notify Team Lead / DPO immediately",IF(G23="No","Escalate to Team Lead - error not corrected","Logged - corrected before release")))
C24: =IF(B24="","",IFERROR(INDEX(Request_Tracker!$B$6:$B$205,MATCH(B24,Request_Tracker!$A$6:$A$205,0)),"Req ID not found")) | H24: =IF(E24<>"Fail","",IF(F24="Wrong recipient","ESCALATE: possible personal data breach - notify Team Lead / DPO immediately",IF(G24="No","Escalate to Team Lead - error not corrected","Logged - corrected before release")))
C25: =IF(B25="","",IFERROR(INDEX(Request_Tracker!$B$6:$B$205,MATCH(B25,Request_Tracker!$A$6:$A$205,0)),"Req ID not found")) | H25: =IF(E25<>"Fail","",IF(F25="Wrong recipient","ESCALATE: possible personal data breach - notify Team Lead / DPO immediately",IF(G25="No","Escalate to Team Lead - error not corrected","Logged - corrected before release")))
C26: =IF(B26="","",IFERROR(INDEX(Request_Tracker!$B$6:$B$205,MATCH(B26,Request_Tracker!$A$6:$A$205,0)),"Req ID not found")) | H26: =IF(E26<>"Fail","",IF(F26="Wrong recipient","ESCALATE: possible personal data breach - notify Team Lead / DPO immediately",IF(G26="No","Escalate to Team Lead - error not corrected","Logged - corrected before release")))
C27: =IF(B27="","",IFERROR(INDEX(Request_Tracker!$B$6:$B$205,MATCH(B27,Request_Tracker!$A$6:$A$205,0)),"Req ID not found")) | H27: =IF(E27<>"Fail","",IF(F27="Wrong recipient","ESCALATE: possible personal data breach - notify Team Lead / DPO immediately",IF(G27="No","Escalate to Team Lead - error not corrected","Logged - corrected before release")))
C28: =IF(B28="","",IFERROR(INDEX(Request_Tracker!$B$6:$B$205,MATCH(B28,Request_Tracker!$A$6:$A$205,0)),"Req ID not found")) | H28: =IF(E28<>"Fail","",IF(F28="Wrong recipient","ESCALATE: possible personal data breach - notify Team Lead / DPO immediately",IF(G28="No","Escalate to Team Lead - error not corrected","Logged - corrected before release")))
... C204: =IF(B204="","",IFERROR(INDEX(Request_Tracker!$B$6:$B$205,MATCH(B204,Request_Tracker!$A$6:$A$205,0)),"Req ID not found")) | H204: =IF(E204<>"Fail","",IF(F204="Wrong recipient","ESCALATE: possible personal data breach - notify Team Lead / DPO immediately",IF(G204="No","Escalate to Team Lead - error not corrected","Logged - corrected before release")))

Sheet Handover_Log
A1: Shift Handover Log
A2: Shared-services handover: nothing at risk is left unannounced. SAMPLE rows 6-8.
A3: Live: open requests due within 1 working day -> | E3: =COUNTIFS(Request_Tracker!$K$6:$K$205,"Open - within SLA",Request_Tracker!$G$6:$G$205,"<="&WORKDAY(Lists!$E$4,1,Lists!$L$4:$L$13)) -> 3
A5: Date | B5: Shift | C5: Handed Over By | D5: Handed Over To | E5: Open Items Handed Over | F5: At-Risk Req IDs | G5: Priority Actions for Next Shift | H5: Customer Comms Pending? | I5: Escalations Raised | J5: Acknowledged by Receiving Agent?
A6: 46295 | B6: Shift A (13:30-22:30 IST) | C6: Agent 1 | D6: Agent 2 | E6: 3 | F6: REQ-0009 | G6: Complete QC on REQ-0009; chase new-coach confirmation for REQ-0010 | H6: Yes | I6: None | J6: Yes
A7: 46296 | B7: Shift A (13:30-22:30 IST) | C7: Agent 2 | D7: Agent 1 | E7: 4 | F7: REQ-0009, REQ-0010 | G7: Issue REQ-0009 before 22:30 IST; confirm coach for REQ-0010 | H7: No | I7: REQ-0010 to Team Lead (coach not responding) | J7: Yes
A8: 46297 | B8: Shift B (14:00-23:00 IST) | C8: Agent 1 | D8: Agent 2 | E8: 4 | F8: REQ-0012 | G8: Salary certificate REQ-0012 due next working day - verify amount, four-eyes check | H8: Yes | I8: None | J8: No

Sheet Worker_History
A1: Worker History - effective dating & as-of lookup
A2: Workday-style concept (synthetic). Try E1003 as-of 01-Jan-2020 (Senior Consultant, Audit) vs 01-Jan-2023 (Manager, Advisory): data depends on the date. E1004 as-of 31-May-2023 = title at leaving.
A4: Emp ID | B4: Effective Date | C4: Event | D4: Job Title | E4: Department | F4: Grade | H4: AS-OF LOOKUP
A5: E1001 | B5: 43528 | C5: Hire | D5: Analyst | E5: Audit | F5: Associate | H5: Emp ID | I5: E1004
A6: E1001 | B6: 44287 | C6: Promotion | D6: Consultant | E6: Audit | F6: Associate | H6: As-of date | I6: 45077
A7: E1001 | B7: 45108 | C7: Promotion | D7: Senior Consultant | E7: Audit | F7: Senior | H7: Effective record date | I7: =IF(OR($I$5="",$I$6=""),"",IF(SUMPRODUCT(MAX(($A$5:$A$104=$I$5)*($B$5:$B$104<=$I$6)*$B$5:$B$104))=0,"No record as of that date",SUMPRODUCT(MAX(($A$5:$A$104=$I$5)*($B$5:$B$104<=$I$6)*$B$5:$B$104)))) -> 45077
A8: E1003 | B8: 42387 | C8: Hire | D8: Consultant | E8: Audit | F8: Associate | H8: Job title | I8: =IF($I$12=0,"",INDEX($D$1:$D$104,$I$12)) -> Consultant
A9: E1003 | B9: 43647 | C9: Promotion | D9: Senior Consultant | E9: Audit | F9: Senior | H9: Department | I9: =IF($I$12=0,"",INDEX($E$1:$E$104,$I$12)) -> Audit
A10: E1003 | B10: 44562 | C10: Transfer + Promotion | D10: Manager | E10: Advisory | F10: Manager | H10: Grade | I10: =IF($I$12=0,"",INDEX($F$1:$F$104,$I$12)) -> Associate
A11: E1004 | B11: 43252 | C11: Hire | D11: Analyst | E11: Audit | F11: Associate | H11: Event | I11: =IF($I$12=0,"",INDEX($C$1:$C$104,$I$12)) -> Termination
A12: E1004 | B12: 44105 | C12: Promotion | D12: Consultant | E12: Audit | F12: Associate | H12: Row (helper) | I12: =IF(ISNUMBER($I$7),SUMPRODUCT(($A$5:$A$104=$I$5)*($B$5:$B$104=$I$7)*ROW($A$5:$A$104)),0) -> 13
A13: E1004 | B13: 45077 | C13: Termination | D13: Consultant | E13: Audit | F13: Associate

Sheet Workday_Concepts
A1: Workday-style concepts (conceptual - not a tenant)
A2: Learning aid. Names, security and processes differ by organisation. No live Workday tenant was used to build this project.
A4: Term | B4: Plain-English meaning | C4: Why it matters in HRSS | D4: Where it appears in this project
A5: Employee ID / Worker | B5: Unique identifier for each person in the HR system. | C5: Search by ID, not name, to avoid mix-ups between similar names. | D5: Emp ID column on every sheet
A6: Worker status | B6: Whether the person is active, on leave or terminated. | C6: Drives eligibility - e.g. salary certificates are for active employees only. | D6: Status column; Letter_Generator readiness check
A7: Effective date | B7: The date a change takes effect (can be past or future). | C7: A reference letter must show title/department as at the correct date. | D7: Worker_History as-of lookup
A8: Supervisory organisation | B8: The reporting hierarchy / team structure under a manager. | C8: Shows department and reporting line for letters and routing. | D8: Department column
A9: Business process | B9: A configured workflow (initiate -> approve -> complete) for an HR event. | C9: Know who must approve before data is changed; avoid bypassing approvals. | D9: Process catalogue below; SOPs
A10: Inbox task | B10: An action item sent to a processor or approver. | C10: Request timing often starts when the task or case arrives - drives SLA. | D10: Date Received / Request_Tracker
A11: Security domain / group | B11: Rules controlling who can see or edit certain data (e.g. compensation). | C11: Why salary data is restricted and purpose-limited. | D11: Salary column marked RESTRICTED
A12: Report (custom / RaaS-style) | B12: A saved report on worker data used for lookups and audits. | C12: Source of truth for verifying details before issuing documents. | D12: Employees sheet mimics a worker report
A13: Job profile / business title | B13: Standard job definition vs the title displayed to others. | C13: Letters must use the correct, approved title. | D13: Job Title column; Worker_History
A14: Case | B14: A tracked service request in HR case management. | C14: Every request needs an owner, timestamps and closure. | D14: Each Request_Tracker row
A17: Illustrative process catalogue - the 6 HRSS tasks (assumed; tenant-specific in real life)
A18: HRSS task | B18: Typical HR-system area (illustrative) | C18: Typical steps | D18: Data sensitivity / key control
A19: Reference letter | B19: Worker profile and reports (view-only); effective-dated job data | C19: Verify requester -> look up hire/end dates and title as at effective date -> generate -> four-eyes check -> send | D19: Medium - facts only; correct recipient
A20: Salary certificate | B20: Compensation data (restricted security domain) | C20: Verify requester and purpose -> confirm active status -> verify gross salary -> second check -> send to employee only | D20: HIGH - restricted; purpose limitation
A21: Coach change | B21: Assignment / relationship update (often tenant-specific or custom) | C21: Validate new coach -> confirm with coach -> update assignment -> notify all parties | D21: Medium - need-to-know on reason
A22: Bike to Work | B22: Benefits / scheme administration with provider and payroll hand-off | C22: Check eligibility and cap -> approve -> hand to scheme provider/payroll -> track | D22: Medium - financial data; audit evidence
A23: Eyecare / VDU voucher | B23: Health & safety entitlement (may sit outside the HR system) | C23: Check VDU flag and gap -> issue code -> record expiry | D23: Medium - record entitlement only, never results
A24: Personal milestones | B24: Recognition; life-event data may be restricted | C24: Verify event -> verify delivery details -> personalise message -> order/issue -> record dispatch | D24: HIGH - sensitive life events; need-to-know

Sheet Employees
A1: Employees (synthetic)
A2: Stands in for a Workday worker report. Salary column is RESTRICTED data - exclude from general support views.
A4: Emp ID | B4: Name | C4: Email | D4: Job Title | E4: Grade | F4: Department | G4: Hire Date | H4: End Date | I4: Status | J4: Coach ID | K4: VDU User? | L4: Annual Salary (EUR) - RESTRICTED
A5: E1001 | B5: Aoife Murphy | C5: aoife.murphy@example.com | D5: Senior Consultant | E5: Senior | F5: Audit | G5: 43528 | I5: active | J5: E1005 | K5: Yes | L5: 68000
A6: E1002 | B6: Conor Walsh | C6: conor.walsh@example.com | D6: Analyst | E6: Associate | F6: Tax | G6: 44816 | I6: active | J6: E1005 | K6: Yes | L6: 42000
A7: E1003 | B7: Niamh Byrne | C7: niamh.byrne@example.com | D7: Manager | E7: Manager | F7: Advisory | G7: 42387 | I7: active | J7: E1006 | K7: Yes | L7: 89000
A8: E1004 | B8: Sean Doyle | C8: sean.doyle@example.com | D8: Consultant | E8: Associate | F8: Audit | G8: 43252 | H8: 45077 | I8: former | K8: No | L8: 52000
A9: E1005 | B9: Ciara Kelly | C9: ciara.kelly@example.com | D9: Senior Manager | E9: Senior Manager | F9: Audit | G9: 41204 | I9: active | K9: Yes | L9: 112000
A10: E1006 | B10: Liam O'Brien | C10: liam.obrien@example.com | D10: Director | E10: Director | F10: Advisory | G10: 40224 | I10: active | K10: Yes | L10: 145000
A11: E1007 | B11: Emma Ryan | C11: emma.ryan@example.com | D11: Analyst | E11: Associate | F11: Tax | G11: 44382 | I11: active | J11: E1006 | K11: No | L11: 40000
A12: E1008 | B12: Patrick Nolan | C12: patrick.nolan@example.com | D12: Associate | E12: Associate | F12: Audit | G12: 41743 | H12: 43434 | I12: former | K12: Yes | L12: 45000

Sheet Lists
A1: Lists & Business Rules
A2: Edit blue cells to change rules; all sheets update. Illustrative assumptions - verify against real policy.
A3: Request Type | B3: SLA (working days) | D3: Parameter | E3: Value | F3: Note | H3: Milestone Event | I3: Gift Type | J3: Value (EUR) | L3: Irish public holidays 2026 (sample) | N3: Lawful purpose of access | P3: Scheme status | R3: Bike item type
A4: Reference Letter | B4: 2 | D4: Report date | E4: =TODAY() -> 46297 | F4: Overwrite with a fixed date to freeze reports | H4: Baby | I4: Baby gift hamper | J4: 75 | L4: 46023 | N4: Employee-requested document | P4: Pending | R4: Bike
A5: Salary Certificate | B5: 1 | D5: Bike to Work cap - bike (EUR) | E5: 1500 | F5: Assumption - verify against current scheme rules | H5: Wedding | I5: Perx voucher | J5: 100 | L5: 46055 | N5: Benefit administration | P5: Approved | R5: E-bike
A6: Coach Change | B6: 3 | D6: Bike to Work cap - e-bike (EUR) | E6: 1500 | F6: Assumption - verify against current scheme rules | H6: Bereavement | I6: Flowers | J6: 60 | L6: 46098 | N6: Employee recognition | P6: Rejected
A7: Bike to Work | B7: 4 | D7: Bike claim gap (years) | E7: 4 | F7: Assumption - minimum gap between claims | H7: Long service | I7: Perx voucher | J7: 150 | L7: 46118 | N7: Health & safety (VDU) | P7: Completed
A8: Eyecare / VDU Voucher | B8: 2 | D8: Eyecare gap (months) | E8: 24 | F8: Assumption - minimum gap between vouchers | H8: Illness | I8: Flowers | J8: 50 | L8: 46146 | N8: Internal HR administration
A9: Personal Milestone | B9: 3 | D9: Voucher validity (days) | E9: 90 | F9: Assumption | L9: 46174
A10: Ad-hoc / Other | B10: 3 | D10: Max coachees per coach | E10: 15 | F10: Assumption | L10: 46237
D11: Company name | E11: Example Company Ltd (Demo) | F11: Used on letters; placeholder | L11: 46321
L12: 46381
L13: 46382
